Workbook

Sheet Wikidata_upec_chemical_20
A1: docid | B1: title | C1: keyword | D1: wikidata_label | E1: wikidata_qid | F1: bnf_id | G1: p279_path | H1: retry_source | I1: match_stage | J1: is_disambiguation | K1: label_similarity | L1: match_score | M1: p31_types | N1: p31_label | O1: Check
A2: 1006198 | B2: Harmonic mechanical excitations of steady convective instabilities: a means to get more uniform heat transfers in mixed convection flows? | C2: Mixed convection | H2: none | I2: none | J2: no | K2: 0 | L2: 0 | O2: ok
A3: 1006198 | B3: Harmonic mechanical excitations of steady convective instabilities: a means to get more uniform heat transfers in mixed convection flows? | C3: Poiseuille-Rayleigh-BÃ©nard flow | H3: none | I3: none | J3: no | K3: 0 | L3: 0 | O3: ok
A4: 1006198 | B4: Harmonic mechanical excitations of steady convective instabilities: a means to get more uniform heat transfers in mixed convection flows? | C4: Convective instability | D4: Convective instability | E4: Q3268911 | G4: instability > risk source > source > entity | H4: context | I4: context | J4: no | K4: 100 | L4: 111 | O4: ok
A5: 1006198 | B5: Harmonic mechanical excitations of steady convective instabilities: a means to get more uniform heat transfers in mixed convection flows? | C5: Convective instability | D5: Convective instability | E5: Q3268911 | G5: instability > state > phenomenon > occurrent > entity | H5: context | I5: context | J5: no | K5: 100 | L5: 111 | O5: ok
A6: 1006198 | B6: Harmonic mechanical excitations of steady convective instabilities: a means to get more uniform heat transfers in mixed convection flows? | C6: Convective instability | D6: Convective instability | E6: Q3268911 | G6: instability > state > phenomenon > observable entity > entity | H6: context | I6: context | J6: no | K6: 100 | L6: 111 | O6: ok
A7: 1006198 | B7: Harmonic mechanical excitations of steady convective instabilities: a means to get more uniform heat transfers in mixed convection flows? | C7: Convective instability | D7: Convective instability | E7: Q3268911 | G7: instability > state > property > abstract entity > entity | H7: context | I7: context | J7: no | K7: 100 | L7: 111 | O7: ok
A8: 1006198 | B8: Harmonic mechanical excitations of steady convective instabilities: a means to get more uniform heat transfers in mixed convection flows? | C8: Convective instability | D8: Convective instability | E8: Q3268911 | G8: instability > risk source > contributing factor > condition > state | H8: context | I8: context | J8: no | K8: 100 | L8: 111 | O8: ok
A9: 1006198 | B9: Harmonic mechanical excitations of steady convective instabilities: a means to get more uniform heat transfers in mixed convection flows? | C9: Convective instability | D9: Convective instability | E9: Q3268911 | G9: instability > risk source > contributing factor > occurrent > entity | H9: context | I9: context | J9: no | K9: 100 | L9: 111 | O9: ok
A10: 1006198 | B10: Harmonic mechanical excitations of steady convective instabilities: a means to get more uniform heat transfers in mixed convection flows? | C10: Rectangular channel | H10: none | I10: none | J10: no | K10: 0 | L10: 0 | O10: ok
A11: 1006198 | B11: Harmonic mechanical excitations of steady convective instabilities: a means to get more uniform heat transfers in mixed convection flows? | C11: Harmonic inlet excitation | H11: none | I11: none | J11: no | K11: 0 | L11: 0 | O11: ok
A12: 1006198 | B12: Harmonic mechanical excitations of steady convective instabilities: a means to get more uniform heat transfers in mixed convection flows? | C12: CVD | H12: none | I12: none | J12: no | K12: 0 | L12: 0 | O12: ok
A13: 1006198 | B13: Harmonic mechanical excitations of steady convective instabilities: a means to get more uniform heat transfers in mixed convection flows? | C13: 3D numerical simulations | H13: none | I13: none | J13: no | K13: 0 | L13: 0 | O13: ok
A14: 1006198 | B14: Harmonic mechanical excitations of steady convective instabilities: a means to get more uniform heat transfers in mixed convection flows? | C14: Design of experiments | D14: Design of experiments | E14: Q18465858 | H14: context | I14: context | J14: no | K14: 100 | L14: 113 | O14: Ok | P14: No descrption defined | Q14: Correct: Q2334061
A15: 1025697 | B15: Identification of a new pseudo-binary hydroxide during calendar corrosion of (La, Mg)2Ni7-type hydrogen storage alloys for Nickel-Metal Hydride batteries | C15: Corrosion | D15: Corrosion | E15: Q5173028 | H15: context | I15: context | J15: no | K15: 100 | L15: 112 | M15: Q169930 | N15: extended play | O15: Wrong | P15: extended play by Front Line Assembly | Q15: Correct: Q137056
A16: 1025697 | B16: Identification of a new pseudo-binary hydroxide during calendar corrosion of (La, Mg)2Ni7-type hydrogen storage alloys for Nickel-Metal Hydride batteries | C16: Ni-MH batteries | H16: none | I16: none | J16: no | K16: 0 | L16: 0 | O16: ok
A17: 1025697 | B17: Identification of a new pseudo-binary hydroxide during calendar corrosion of (La, Mg)2Ni7-type hydrogen storage alloys for Nickel-Metal Hydride batteries | C17: Raman micro spectroscopy | H17: none | I17: none | J17: no | K17: 0 | L17: 0 | O17: ok
A18: 1025697 | B18: Identification of a new pseudo-binary hydroxide during calendar corrosion of (La, Mg)2Ni7-type hydrogen storage alloys for Nickel-Metal Hydride batteries | C18: TEM | D18: Tem | E18: Q36531 | F18: 12167223r | G18: Gurunsi > Gur > Voltaâ€“Congo > Atlanticâ€“Congo > Nigerâ€“Congo | H18: exact_label | I18: exact_label | J18: no | K18: 100 | L18: 50 | M18: Q1288568;Q34770 | N18: modern language;language | O18: Ok | P18: transmission electron microscopy | Q18: Correct: Q110779037
A19: 1025697 | B19: Identification of a new pseudo-binary hydroxide during calendar corrosion of (La, Mg)2Ni7-type hydrogen storage alloys for Nickel-Metal Hydride batteries | C19: TEM | D19: Tem | E19: Q36531 | F19: 12167223r | G19: Gurunsi > Gur > Nigerâ€“Congo > human language > language | H19: exact_label | I19: exact_label | J19: no | K19: 100 | L19: 50 | M19: Q1288568;Q34770 | N19: modern language;language | O19: Wrong
A20: 1025697 | B20: Identification of a new pseudo-binary hydroxide during calendar corrosion of (La, Mg)2Ni7-type hydrogen storage alloys for Nickel-Metal Hydride batteries | C20: Combination of techniques | H20: none | I20: none | J20: no | K20: 0 | L20: 0 | O20: ok
A21: 1060481 | B21: Ï€-Conjugated sulfonium-based photoacid generators: an integrated molecular approach for efficient one and two-photon polymerization | C21: 20902069 | H21: none | I21: none | J21: no | K21: 0 | L21: 0 | O21: ok
A22: 1060481 | B22: Ï€-Conjugated sulfonium-based photoacid generators: an integrated molecular approach for efficient one and two-photon polymerization | C22: Nsfc | H22: none | I22: none | J22: yes | K22: 0 | L22: 0 | O22: ok
A23: 1060481 | B23: Ï€-Conjugated sulfonium-based photoacid generators: an integrated molecular approach for efficient one and two-photon polymerization | C23: National natural science foundation of china | D23: National Natural Science Foundation of China | E23: Q4501917 | H23: exact_label | I23: exact_label | J23: no | K23: 100 | L23: 50 | M23: Q327333;Q45400320;Q5509032;Q98675100 | N23: open-access publisher;government agency;funding body;vice-ministerial level institution | O23: ok
A24: 1060481 | B24: Ï€-Conjugated sulfonium-based photoacid generators: an integrated molecular approach for efficient one and two-photon polymerization | C24: 21074094 | H24: none | I24: none | J24: no | K24: 0 | L24: 0 | O24: ok
A25: 1060481 | B25: Ï€-Conjugated sulfonium-based photoacid generators: an integrated molecular approach for efficient one and two-photon polymerization | C25: 51173134 | H25: none | I25: none | J25: no | K25: 0 | L25: 0 | O25: ok
A26: 1064801 | B26: Nucleophilic or Electrophilic Interactions of C2 with HX systems (X=F, Cl, Br) | C26: Potential curves | H26: none | I26: none | J26: no | K26: 0 | L26: 0 | O26: ok
A27: 1064801 | B27: Nucleophilic or Electrophilic Interactions of C2 with HX systems (X=F, Cl, Br) | C27: Long range interactions | H27: none | I27: none | J27: no | K27: 0 | L27: 0 | O27: ok
A28: 1064801 | B28: Nucleophilic or Electrophilic Interactions of C2 with HX systems (X=F, Cl, Br) | C28: Ab-initio calculations | H28: none | I28: none | J28: no | K28: 0 | L28: 0 | O28: ok
A29: 1064801 | B29: Nucleophilic or Electrophilic Interactions of C2 with HX systems (X=F, Cl, Br) | C29: Hydrogen halides | D29: hydrogen halide | E29: Q1572088 | G29: halide > ionic compound > chemical compound > pure substance > chemical substance | H29: exact_label | I29: exact_label | J29: no | K29: 100 | L29: 50 | M29: Q47154513 | N29: structural class of chemical entities | O29: ok
A30: 1064801 | B30: Nucleophilic or Electrophilic Interactions of C2 with HX systems (X=F, Cl, Br) | C30: Hydrogen halides | D30: hydrogen halide | E30: Q1572088 | G30: halide > halogen compound > chemical compound > pure substance > chemical substance | H30: exact_label | I30: exact_label | J30: no | K30: 100 | L30: 50 | M30: Q47154513 | N30: structural class of chemical entities | O30: ok
A31: 1064801 | B31: Nucleophilic or Electrophilic Interactions of C2 with HX systems (X=F, Cl, Br) | C31: Hydrogen halides | D31: hydrogen halide | E31: Q1572088 | G31: hydrogen compound > chemical compound > pure substance > chemical substance > chemical entity | H31: exact_label | I31: exact_label | J31: no | K31: 100 | L31: 50 | M31: Q47154513 | N31: structural class of chemical entities | O31: ok
A32: 1064801 | B32: Nucleophilic or Electrophilic Interactions of C2 with HX systems (X=F, Cl, Br) | C32: Hydrogen halides | D32: hydrogen halide | E32: Q1572088 | G32: hydrogen compound > chemical compound > pure substance > chemical substance > substance | H32: exact_label | I32: exact_label | J32: no | K32: 100 | L32: 50 | M32: Q47154513 | N32: structural class of chemical entities | O32: ok
A33: 1064801 | B33: Nucleophilic or Electrophilic Interactions of C2 with HX systems (X=F, Cl, Br) | C33: Hydrogen halides | D33: hydrogen halide | E33: Q1572088 | G33: mineral acid > acid > chemical compound > pure substance > chemical substance | H33: exact_label | I33: exact_label | J33: no | K33: 100 | L33: 50 | M33: Q47154513 | N33: structural class of chemical entities | O33: ok
A34: 1064801 | B34: Nucleophilic or Electrophilic Interactions of C2 with HX systems (X=F, Cl, Br) | C34: Hydrogen halides | D34: hydrogen halide | E34: Q1572088 | G34: mineral acid > inorganic compound > chemical compound > pure substance > chemical substance | H34: exact_label | I34: exact_label | J34: no | K34: 100 | L34: 50 | M34: Q47154513 | N34: structural class of chemical entities | O34: ok
A35: 1064801 | B35: Nucleophilic or Electrophilic Interactions of C2 with HX systems (X=F, Cl, Br) | C35: Hydrogen halides | D35: hydrogen halide | E35: Q1572088 | G35: mineral acid > inorganic compound > inorganic substance > chemical substance > chemical entity | H35: exact_label | I35: exact_label | J35: no | K35: 100 | L35: 50 | M35: Q47154513 | N35: structural class of chemical entities | O35: ok
A36: 1064801 | B36: Nucleophilic or Electrophilic Interactions of C2 with HX systems (X=F, Cl, Br) | C36: Hydrogen halides | D36: hydrogen halide | E36: Q1572088 | G36: mineral acid > inorganic compound > inorganic substance > chemical substance > substance | H36: exact_label | I36: exact_label | J36: no | K36: 100 | L36: 50 | M36: Q47154513 | N36: structural class of chemical entities | O36: ok
A37: 1064801 | B37: Nucleophilic or Electrophilic Interactions of C2 with HX systems (X=F, Cl, Br) | C37: Hydrogen halides | D37: hydrogen halide | E37: Q1572088 | G37: monoprotic acid > acid > chemical compound > pure substance > chemical substance | H37: exact_label | I37: exact_label | J37: no | K37: 100 | L37: 50 | M37: Q47154513 | N37: structural class of chemical entities | O37: ok
A38: 1067996 | B38: In situ analysis of Titan's tholins by Laser 2 steps Desorption Ionisation | C38: 5210 PLANETARY SCIENCES ASTROBIOLOGY Planetary atmospheres | H38: none | I38: none | J38: no | K38: 0 | L38: 0 | O38: ok
A39: 1067996 | B39: In situ analysis of Titan's tholins by Laser 2 steps Desorption Ionisation | C39: Clouds | D39: Clouds | E39: Q110548120 | H39: context | I39: context | J39: no | K39: 100 | L39: 114 | M39: Q11060274;Q18218093;Q838948 | N39: print;etching print;work of art | O39: Wrong
A40: 1067996 | B40: In situ analysis of Titan's tholins by Laser 2 steps Desorption Ionisation | C40: And hazes | H40: none | I40: none | J40: no | K40: 0 | L40: 0 | O40: ok
A41: 1067996 | B41: In situ analysis of Titan's tholins by Laser 2 steps Desorption Ionisation | C41: 5405 PLANETARY SCIENCES SOLID SURFACE PLANETS Atmospheres | H41: none | I41: none | J41: no | K41: 0 | L41: 0 | O41: ok
A42: 1067996 | B42: In situ analysis of Titan's tholins by Laser 2 steps Desorption Ionisation | C42: 0305 ATMOSPHERIC COMPOSITION AND STRUCTURE Aerosols and particles | H42: none | I42: none | J42: no | K42: 0 | L42: 0 | O42: ok
A43: 1078652 | B43: MCMC2 (version 1.1): A Monte Carlo code for multiply-charged clusters | C43: Parallel Charging | H43: none | I43: none | J43: no | K43: 0 | L43: 0 | O43: ok
A44: 1078652 | B44: MCMC2 (version 1.1): A Monte Carlo code for multiply-charged clusters | C44: Parallel Tempering | D44: parallel tempering | E44: Q7135015 | G44: randomized algorithm > algorithm > procedure > method > means | H44: context | I44: context | J44: no | K44: 88.9 | L44: 106.3 | O44: ok
A45: 1078652 | B45: MCMC2 (version 1.1): A Monte Carlo code for multiply-charged clusters | C45: Parallel Tempering | D45: parallel tempering | E45: Q7135015 | G45: randomized algorithm > algorithm > work > artificial object > object | H45: context | I45: context | J45: no | K45: 88.9 | L45: 106.3 | O45: ok
A46: 1078652 | B46: MCMC2 (version 1.1): A Monte Carlo code for multiply-charged clusters | C46: Parallel Tempering | D46: parallel tempering | E46: Q7135015 | G46: randomized algorithm > algorithm > work > cultural artifact > artificial object | H46: context | I46: context | J46: no | K46: 88.9 | L46: 106.3 | O46: ok
A47: 1078652 | B47: MCMC2 (version 1.1): A Monte Carlo code for multiply-charged clusters | C47: Parallel Tempering | D47: parallel tempering | E47: Q7135015 | G47: randomized algorithm > algorithm > work > cultural artifact > cultural heritage | H47: context | I47: context | J47: no | K47: 88.9 | L47: 106.3 | O47: ok
A48: 1078652 | B48: MCMC2 (version 1.1): A Monte Carlo code for multiply-charged clusters | C48: Electrospray ionisation | H48: none | I48: none | J48: no | K48: 0 | L48: 0 | O48: ok
A49: 1078652 | B49: MCMC2 (version 1.1): A Monte Carlo code for multiply-charged clusters | C49: Charged droplets | H49: none | I49: none | J49: no | K49: 0 | L49: 0 | O49: ok
A50: 1078652 | B50: MCMC2 (version 1.1): A Monte Carlo code for multiply-charged clusters | C50: Charged clusters | H50: none | I50: none | J50: no | K50: 0 | L50: 0 | O50: ok
A51: 1078652 | B51: MCMC2 (version 1.1): A Monte Carlo code for multiply-charged clusters | C51: Coarse-grained models | D51: Coarse-grained model | E51: Q25305554 | G51: mathematical model > mathematical object > abstract entity > entity | H51: context | I51: context | J51: no | K51: 97.6 | L51: 109.5 | O51: ok
A52: 1078652 | B52: MCMC2 (version 1.1): A Monte Carlo code for multiply-charged clusters | C52: Coarse-grained models | D52: Coarse-grained model | E52: Q25305554 | G52: mathematical model > conceptual model > knowledge organization system > conceptual system > system | H52: context | I52: context | J52: no | K52: 97.6 | L52: 109.5 | O52: ok
A53: 1078652 | B53: MCMC2 (version 1.1): A Monte Carlo code for multiply-charged clusters | C53: Coarse-grained models | D53: Coarse-grained model | E53: Q25305554 | G53: mathematical model > conceptual model > knowledge organization system > conceptual system > artificial object | H53: context | I53: context | J53: no | K53: 97.6 | L53: 109.5 | O53: ok
A54: 1078652 | B54: MCMC2 (version 1.1): A Monte Carlo code for multiply-charged clusters | C54: Coarse-grained models | D54: Coarse-grained model | E54: Q25305554 | G54: mathematical model > conceptual model > knowledge organization system > conceptual system > abstract entity | H54: context | I54: context | J54: no | K54: 97.6 | L54: 109.5 | O54: ok
A55: 1078652 | B55: MCMC2 (version 1.1): A Monte Carlo code for multiply-charged clusters | C55: Coarse-grained models | D55: Coarse-grained model | E55: Q25305554 | G55: mathematical model > conceptual model > knowledge organization system > conceptual system > concept | H55: context | I55: context | J55: no | K55: 97.6 | L55: 109.5 | O55: ok
A56: 1078652 | B56: MCMC2 (version 1.1): A Monte Carlo code for multiply-charged clusters | C56: Coarse-grained models | D56: Coarse-grained model | E56: Q25305554 | G56: mathematical model > conceptual model > knowledge organization system > model > artificial object | H56: context | I56: context | J56: no | K56: 97.6 | L56: 109.5 | O56: ok
A57: 1078652 | B57: MCMC2 (version 1.1): A Monte Carlo code for multiply-charged clusters | C57: Coarse-grained models | D57: Coarse-grained model | E57: Q25305554 | G57: mathematical model > conceptual model > knowledge organization system > model > information | H57: context | I57: context | J57: no | K57: 97.6 | L57: 109.5 | O57: ok
A58: 1078652 | B58: MCMC2 (version 1.1): A Monte Carlo code for multiply-charged clusters | C58: Coarse-grained models | D58: Coarse-grained model | E58: Q25305554 | G58: mathematical model > conceptual model > knowledge organization system > reference work > tertiary source | H58: context | I58: context | J58: no | K58: 97.6 | L58: 109.5 | O58: ok
A59: 1078652 | B59: MCMC2 (version 1.1): A Monte Carlo code for multiply-charged clusters | C59: Coarse-grained models | D59: Coarse-grained model | E59: Q25305554 | G59: mathematical model > conceptual model > knowledge organization system > reference work > learning material | H59: context | I59: context | J59: no | K59: 97.6 | L59: 109.5 | O59: ok
A60: 1078652 | B60: MCMC2 (version 1.1): A Monte Carlo code for multiply-charged clusters | C60: Coarse-grained models | D60: Coarse-grained model | E60: Q25305554 | G60: mathematical model > conceptual model > knowledge organization system > reference work > creative work | H60: context | I60: context | J60: no | K60: 97.6 | L60: 109.5 | O60: ok
A61: 1078652 | B61: MCMC2 (version 1.1): A Monte Carlo code for multiply-charged clusters | C61: Coarse-grained models | D61: Coarse-grained model | E61: Q25305554 | G61: mathematical model > conceptual model > knowledge organization system > reference work > document | H61: context | I61: context | J61: no | K61: 97.6 | L61: 109.5 | O61: ok
A62: 1078652 | B62: MCMC2 (version 1.1): A Monte Carlo code for multiply-charged clusters | C62: Coarse-grained models | D62: Coarse-grained model | E62: Q25305554 | G62: mathematical model > conceptual model > knowledge organization system > reference work > written work | H62: context | I62: context | J62: no | K62: 97.6 | L62: 109.5 | O62: ok
... A79: 1078652 | B79: MCMC2 (version 1.1): A Monte Carlo code for multiply-charged clusters | C79: Coarse-grained models | D79: Coarse-grained model | E79: Q25305554 | G79: mathematical model > mathematical object > scientific object > object > entity | H79: context | I79: context | J79: no | K79: 97.6 | L79: 109.5 | O79: ok
A80: 1078652 | B80: MCMC2 (version 1.1): A Monte Carlo code for multiply-charged clusters | C80: Monte Carlo simulations | D80: Monte Carlo Simulation Studies | E80: Q57429452 | H80: context | I80: context | J80: no | K80: 83 | L80: 52.8 | M80: Q1980247 | N80: chapter | O80: Wrong | P80: Chapter in a book
A81: 1078896 | B81: Are there Stable Excited Triplet States of NCS-/CNS- and NCO-/CNO-? | C81: Potential energy functions | H81: none | I81: none | J81: no | K81: 0 | L81: 0 | O81: ok
A82: 1078896 | B82: Are there Stable Excited Triplet States of NCS-/CNS- and NCO-/CNO-? | C82: Excited states | D82: excited state | E82: Q215328 | H82: context | I82: context | J82: no | K82: 88.9 | L82: 110.3 | M82: Q669532 | N82: energy level | O82: ok
A83: 1078896 | B83: Are there Stable Excited Triplet States of NCS-/CNS- and NCO-/CNO-? | C83: Molecular anions | H83: none | I83: none | J83: no | K83: 0 | L83: 0 | O83: ok
A84: 1083001 | B84: 245 - A highly sensitive glucose electrode using glucose oxidase collagen film | C84: Glocose oxidase | H84: none | I84: none | J84: no | K84: 0 | L84: 0 | O84: ok
A85: 1083001 | B85: 245 - A highly sensitive glucose electrode using glucose oxidase collagen film | C85: Amperometric biosensor | H85: none | I85: none | J85: no | K85: 0 | L85: 0 | O85: ok
A86: 1083001 | B86: 245 - A highly sensitive glucose electrode using glucose oxidase collagen film | C86: Collagen | D86: collagen | E86: Q26868 | G86: protein-containing complex > cellular component > component > part > entity | H86: context | I86: context | J86: no | K86: 87.5 | L86: 106.5 | M86: Q5058355;Q78155096 | N86: family of protein complexes;cellular component | O86: ok
A87: 1083001 | B87: 245 - A highly sensitive glucose electrode using glucose oxidase collagen film | C87: Collagen | D87: collagen | E87: Q26868 | G87: protein-containing complex > cellular component > component > perceptible physical object > physical object | H87: context | I87: context | J87: no | K87: 87.5 | L87: 106.5 | M87: Q5058355;Q78155096 | N87: family of protein complexes;cellular component | O87: ok
A88: 1083001 | B88: 245 - A highly sensitive glucose electrode using glucose oxidase collagen film | C88: Collagen | D88: collagen | E88: Q26868 | G88: protein-containing complex > cellular component > component > material entity > independent continuant | H88: context | I88: context | J88: no | K88: 87.5 | L88: 106.5 | M88: Q5058355;Q78155096 | N88: family of protein complexes;cellular component | O88: ok
A89: 1083001 | B89: 245 - A highly sensitive glucose electrode using glucose oxidase collagen film | C89: Collagen | D89: collagen | E89: Q26868 | G89: protein-containing complex > cellular component > cardinal cell part > anatomical structure > biological structure | H89: context | I89: context | J89: no | K89: 87.5 | L89: 106.5 | M89: Q5058355;Q78155096 | N89: family of protein complexes;cellular component | O89: ok
A90: 1083001 | B90: 245 - A highly sensitive glucose electrode using glucose oxidase collagen film | C90: Collagen | D90: collagen | E90: Q26868 | G90: protein-containing complex > cellular component > cardinal cell part > anatomical structure > material anatomical entity | H90: context | I90: context | J90: no | K90: 87.5 | L90: 106.5 | M90: Q5058355;Q78155096 | N90: family of protein complexes;cellular component | O90: ok
A91: 1083001 | B91: 245 - A highly sensitive glucose electrode using glucose oxidase collagen film | C91: Collagen | D91: collagen | E91: Q26868 | G91: protein-containing complex > oligomer > multimer > chemical compound > pure substance | H91: context | I91: context | J91: no | K91: 87.5 | L91: 106.5 | M91: Q5058355;Q78155096 | N91: family of protein complexes;cellular component | O91: ok
A92: 1083001 | B92: 245 - A highly sensitive glucose electrode using glucose oxidase collagen film | C92: Collagen | D92: collagen | E92: Q26868 | G92: fibrous protein > protein > biopolymer > polymer > mixture | H92: context | I92: context | J92: no | K92: 87.5 | L92: 106.5 | M92: Q5058355;Q78155096 | N92: family of protein complexes;cellular component | O92: ok
A93: 1083001 | B93: 245 - A highly sensitive glucose electrode using glucose oxidase collagen film | C93: Collagen | D93: collagen | E93: Q26868 | G93: fibrous protein > protein > biopolymer > polymer > material | H93: context | I93: context | J93: no | K93: 87.5 | L93: 106.5 | M93: Q5058355;Q78155096 | N93: family of protein complexes;cellular component | O93: ok
A94: 1083001 | B94: 245 - A highly sensitive glucose electrode using glucose oxidase collagen film | C94: Collagen | D94: collagen | E94: Q26868 | G94: fibrous protein > protein > biopolymer > biological macromolecule > anatomical structure | H94: context | I94: context | J94: no | K94: 87.5 | L94: 106.5 | M94: Q5058355;Q78155096 | N94: family of protein complexes;cellular component | O94: ok
A95: 1083001 | B95: 245 - A highly sensitive glucose electrode using glucose oxidase collagen film | C95: Collagen | D95: collagen | E95: Q26868 | G95: fibrous protein > protein > biopolymer > biological macromolecule > macromolecule | H95: context | I95: context | J95: no | K95: 87.5 | L95: 106.5 | M95: Q5058355;Q78155096 | N95: family of protein complexes;cellular component | O95: ok
A96: 1083001 | B96: 245 - A highly sensitive glucose electrode using glucose oxidase collagen film | C96: Collagen | D96: collagen | E96: Q26868 | G96: fibrous protein > protein > biopolymer > biological macromolecule > biomolecule | H96: context | I96: context | J96: no | K96: 87.5 | L96: 106.5 | M96: Q5058355;Q78155096 | N96: family of protein complexes;cellular component | O96: ok
A97: 1083001 | B97: 245 - A highly sensitive glucose electrode using glucose oxidase collagen film | C97: Collagen | D97: collagen | E97: Q26868 | G97: fibrous protein > protein > gene product > organic compound > carbon compound | H97: context | I97: context | J97: no | K97: 87.5 | L97: 106.5 | M97: Q5058355;Q78155096 | N97: family of protein complexes;cellular component | O97: ok
... A114: 1083001 | B114: 245 - A highly sensitive glucose electrode using glucose oxidase collagen film | C114: Collagen | D114: collagen | E114: Q26868 | G114: extracellular matrix proteins > fibrous protein > protein > biological macromolecule > biomolecule | H114: context | I114: context | J114: no | K114: 87.5 | L114: 106.5 | M114: Q5058355;Q78155096 | N114: family of protein complexes;cellular component | O114: ok
A115: 1083001 | B115: 245 - A highly sensitive glucose electrode using glucose oxidase collagen film | C115: Biosensors | D115: Biosensors | E115: Q27709294 | H115: context | I115: context | J115: no | K115: 100 | L115: 110 | M115: Q5633421 | N115: scientific journal | O115: Wrong | P115: journal
A116: 1083004 | B116: Electrochemical biosensors: Recommended definitions and classification (Technical Report) | C116: Electrochemical biosensor | H116: none | I116: none | J116: no | K116: 0 | L116: 0 | O116: ok
A117: 1083004 | B117: Electrochemical biosensors: Recommended definitions and classification (Technical Report) | C117: Classification | D117: classification | E117: Q5128386 | G117: stylistic device > rhetorical device > technique > method > means | H117: context | I117: context | J117: no | K117: 92.9 | L117: 109.7 | O117: ok
A118: 1083004 | B118: Electrochemical biosensors: Recommended definitions and classification (Technical Report) | C118: Classification | D118: classification | E118: Q5128386 | G118: stylistic device > rhetorical device > technique > activity > process | H118: context | I118: context | J118: no | K118: 92.9 | L118: 109.7 | O118: ok
A119: 1083004 | B119: Electrochemical biosensors: Recommended definitions and classification (Technical Report) | C119: Definition | D119: Definition | E119: Q16247949 | H119: context | I119: context | J119: no | K119: 100 | L119: 113 | M119: Q169930 | N119: extended play | O119: Wrong | P119: 2001 extended play by Jersey | Q119: Correct: Q101072
A120: 1083007 | B120: Problems in Adapting a Glucose-Oxidase Electrochemical Sensor into an Implantable Glucose-Sensing Device | C120: Electrochemical biosensor | H120: none | I120: none | J120: no | K120: 0 | L120: 0 | O120: ok
A121: 1083007 | B121: Problems in Adapting a Glucose-Oxidase Electrochemical Sensor into an Implantable Glucose-Sensing Device | C121: Implantable sensor | D121: Implantable sensor | E121: Q124665234 | H121: context | I121: context | J121: no | K121: 100 | L121: 112 | M121: Q43305660 | N121: United States patent | O121: Wrong | P121: United States patent
A122: 1083007 | B122: Problems in Adapting a Glucose-Oxidase Electrochemical Sensor into an Implantable Glucose-Sensing Device | C122: Glucose | D122: glucose | E122: Q37525 | G122: aldohexose > aldose > monosaccharide > carbohydrate > polyol | H122: context | I122: context | J122: no | K122: 85.7 | L122: 103.4 | M122: Q136192523;Q15711994 | N122: group of isomeric entities;simple carbohydrates | O122: ok
A123: 1083007 | B123: Problems in Adapting a Glucose-Oxidase Electrochemical Sensor into an Implantable Glucose-Sensing Device | C123: Glucose | D123: glucose | E123: Q37525 | G123: aldohexose > aldose > monosaccharide > carbohydrate > carbohydrate derivative | H123: context | I123: context | J123: no | K123: 85.7 | L123: 103.4 | M123: Q136192523;Q15711994 | N123: group of isomeric entities;simple carbohydrates | O123: ok
A124: 1083007 | B124: Problems in Adapting a Glucose-Oxidase Electrochemical Sensor into an Implantable Glucose-Sensing Device | C124: Glucose | D124: glucose | E124: Q37525 | G124: aldohexose > aldose > aldehydes > carbonyl compound > organooxygen compound | H124: context | I124: context | J124: no | K124: 85.7 | L124: 103.4 | M124: Q136192523;Q15711994 | N124: group of isomeric entities;simple carbohydrates | O124: ok
A125: 1083007 | B125: Problems in Adapting a Glucose-Oxidase Electrochemical Sensor into an Implantable Glucose-Sensing Device | C125: Glucose | D125: glucose | E125: Q37525 | G125: aldohexose > aldose > aldehydes > carbonyl compound > oxo compound | H125: context | I125: context | J125: no | K125: 85.7 | L125: 103.4 | M125: Q136192523;Q15711994 | N125: group of isomeric entities;simple carbohydrates | O125: ok
A126: 1083007 | B126: Problems in Adapting a Glucose-Oxidase Electrochemical Sensor into an Implantable Glucose-Sensing Device | C126: Glucose | D126: glucose | E126: Q37525 | G126: aldohexose > hexose > monosaccharide > carbohydrate > polyol | H126: context | I126: context | J126: no | K126: 85.7 | L126: 103.4 | M126: Q136192523;Q15711994 | N126: group of isomeric entities;simple carbohydrates | O126: ok
A127: 1083007 | B127: Problems in Adapting a Glucose-Oxidase Electrochemical Sensor into an Implantable Glucose-Sensing Device | C127: Glucose | D127: glucose | E127: Q37525 | G127: aldohexose > hexose > monosaccharide > carbohydrate > carbohydrate derivative | H127: context | I127: context | J127: no | K127: 85.7 | L127: 103.4 | M127: Q136192523;Q15711994 | N127: group of isomeric entities;simple carbohydrates | O127: ok
A128: 1083007 | B128: Problems in Adapting a Glucose-Oxidase Electrochemical Sensor into an Implantable Glucose-Sensing Device | C128: Glucose oxidase | D128: Glucose oxidase | E128: Q61497978 | G128: protein > biopolymer > polymer > mixture > chemical substance | H128: context | I128: context | J128: no | K128: 100 | L128: 111 | M128: Q8054 | N128: protein | O128: ok
A129: 1083007 | B129: Problems in Adapting a Glucose-Oxidase Electrochemical Sensor into an Implantable Glucose-Sensing Device | C129: Glucose oxidase | D129: Glucose oxidase | E129: Q61497978 | G129: protein > biopolymer > polymer > material > substance | H129: context | I129: context | J129: no | K129: 100 | L129: 111 | M129: Q8054 | N129: protein | O129: ok
A130: 1083007 | B130: Problems in Adapting a Glucose-Oxidase Electrochemical Sensor into an Implantable Glucose-Sensing Device | C130: Glucose oxidase | D130: Glucose oxidase | E130: Q61497978 | G130: protein > biopolymer > polymer > material > product | H130: context | I130: context | J130: no | K130: 100 | L130: 111 | M130: Q8054 | N130: protein | O130: ok
A131: 1083007 | B131: Problems in Adapting a Glucose-Oxidase Electrochemical Sensor into an Implantable Glucose-Sensing Device | C131: Glucose oxidase | D131: Glucose oxidase | E131: Q61497978 | G131: protein > biopolymer > biological macromolecule > anatomical structure > biological structure | H131: context | I131: context | J131: no | K131: 100 | L131: 111 | M131: Q8054 | N131: protein | O131: ok
A132: 1083007 | B132: Problems in Adapting a Glucose-Oxidase Electrochemical Sensor into an Implantable Glucose-Sensing Device | C132: Glucose oxidase | D132: Glucose oxidase | E132: Q61497978 | G132: protein > biopolymer > biological macromolecule > anatomical structure > material anatomical entity | H132: context | I132: context | J132: no | K132: 100 | L132: 111 | M132: Q8054 | N132: protein | O132: ok
...

Sheet Wikidata_upec_civil_20
A1: docid | B1: title | C1: keyword | D1: wikidata_label | E1: wikidata_qid | F1: bnf_id | G1: p279_path | H1: retry_source | I1: match_stage | J1: is_disambiguation | K1: label_similarity | L1: match_score | M1: p31_types | N1: p31_label | O1: Check | S1: clean | T1: Sclean
A2: 1002652 | B2: Urban stormwater source control policies: why and how? | C2: Stormwater management | H2: none | I2: none | J2: no | K2: 0 | L2: 0 | P2: csv empty, no info on wikidata | Q2: yes | S2: =LOWER(TRIM(CLEAN(Q2))) -> yes | T2: =IF(S2="","",LOWER(TRIM(S2))) -> yes
A3: 1002652 | B3: Urban stormwater source control policies: why and how? | C3: Urban areas | D3: urban area | E3: Q702492 | G3: human settlement > populated place > region > geographical feature > geographic entity | H3: exact_label | I3: exact_label | J3: no | K3: 100 | L3: 50 | Q3: yes | S3: =LOWER(TRIM(CLEAN(Q3))) -> yes | T3: =IF(S3="","",LOWER(TRIM(S3))) -> yes
A4: 1002652 | B4: Urban stormwater source control policies: why and how? | C4: Urban areas | D4: urban area | E4: Q702492 | G4: human settlement > populated place > region > geographical feature > concrete object | H4: exact_label | I4: exact_label | J4: no | K4: 100 | L4: 50 | Q4: yes | S4: =LOWER(TRIM(CLEAN(Q4))) -> yes | T4: =IF(S4="","",LOWER(TRIM(S4))) -> yes
A5: 1002652 | B5: Urban stormwater source control policies: why and how? | C5: Urban areas | D5: urban area | E5: Q702492 | G5: human settlement > populated place > region > geographical feature > physical location | H5: exact_label | I5: exact_label | J5: no | K5: 100 | L5: 50 | Q5: yes | S5: =LOWER(TRIM(CLEAN(Q5))) -> yes | T5: =IF(S5="","",LOWER(TRIM(S5))) -> yes
A6: 1002652 | B6: Urban stormwater source control policies: why and how? | C6: Urban areas | D6: urban area | E6: Q702492 | G6: human settlement > populated place > artificial geographic entity > geographic entity > geolocatable entity | H6: exact_label | I6: exact_label | J6: no | K6: 100 | L6: 50 | Q6: yes | S6: =LOWER(TRIM(CLEAN(Q6))) -> yes | T6: =IF(S6="","",LOWER(TRIM(S6))) -> yes | U6: 1st round | V6: Field | W6: Total articles | X6: Total keywords | Y6: Correct Wikidata label | Z6: Incorrect Wikidata label | AA6: # QID in Wikidata | AB6: # BNF_Id | AC6: % Correct Wikidata label | AD6: % Incorrect Wikidata label | AE6: % # QID in Wikidata | AF6: % # BNF_Id
A7: 1002652 | B7: Urban stormwater source control policies: why and how? | C7: Urban areas | D7: urban area | E7: Q702492 | G7: human settlement > populated place > artificial geographic entity > geographic entity > region of space | H7: exact_label | I7: exact_label | J7: no | K7: 100 | L7: 50 | Q7: yes | S7: =LOWER(TRIM(CLEAN(Q7))) -> yes | T7: =IF(S7="","",LOWER(TRIM(S7))) -> yes | U7: Sallay | V7: Civil Engineering | W7: 20 | X7: {=COUNTA(_xlfn.UNIQUE(_xlfn._xlws.FILTER(C2:C389, C2:C389<>"")))} -> 93 | Y7: {=COUNTA(_xlfn.UNIQUE(_xlfn._xlws.FILTER(C2:C389 & E2:E389, T2:T389="yes")))} -> 67 | Z7: {=COUNTA(_xlfn.UNIQUE(_xlfn._xlws.FILTER(C2:C389 & E2:E389, T2:T389="wrong")))} -> 26 | AA7: {=COUNTA(_xlfn.UNIQUE(_xlfn._xlws.FILTER(E2:E389, E2:E389<>"")))} -> 43 | AB7: {=COUNTA(_xlfn.UNIQUE(_xlfn._xlws.FILTER(F2:F389, F2:F389<>"")))} -> 7 | AC7: =Y7 / (Y7 + Z7) -> 0.72043011 | AD7: =Z7 / (Y7 + Z7) -> 0.27956989 | AE7: =AA7 / X7 -> 0.46236559 | AF7: =AB7 / X7 -> 0.075268817
A8: 1002652 | B8: Urban stormwater source control policies: why and how? | C8: Urban areas | D8: urban area | E8: Q702492 | G8: human settlement > populated place > artificial geographic entity > artificial object > object | H8: exact_label | I8: exact_label | J8: no | K8: 100 | L8: 50 | Q8: yes | S8: =LOWER(TRIM(CLEAN(Q8))) -> yes | T8: =IF(S8="","",LOWER(TRIM(S8))) -> yes
A9: 1002652 | B9: Urban stormwater source control policies: why and how? | C9: Urban areas | D9: urban area | E9: Q702492 | G9: human settlement > group of structures or buildings > group of artificial physical objects > group of physical objects > group or class of physical objects | H9: exact_label | I9: exact_label | J9: no | K9: 100 | L9: 50 | Q9: yes | S9: =LOWER(TRIM(CLEAN(Q9))) -> yes | T9: =IF(S9="","",LOWER(TRIM(S9))) -> yes
A10: 1002652 | B10: Urban stormwater source control policies: why and how? | C10: Urban areas | D10: urban area | E10: Q702492 | G10: human settlement > group of structures or buildings > group of artificial physical objects > group of physical objects > group | H10: exact_label | I10: exact_label | J10: no | K10: 100 | L10: 50 | Q10: yes | S10: =LOWER(TRIM(CLEAN(Q10))) -> yes | T10: =IF(S10="","",LOWER(TRIM(S10))) -> yes
A11: 1002652 | B11: Urban stormwater source control policies: why and how? | C11: Urban areas | D11: urban area | E11: Q702492 | G11: human settlement > group of structures or buildings > group of geographic locations > group > set | H11: exact_label | I11: exact_label | J11: no | K11: 100 | L11: 50 | Q11: yes | S11: =LOWER(TRIM(CLEAN(Q11))) -> yes | T11: =IF(S11="","",LOWER(TRIM(S11))) -> yes
A12: 1002652 | B12: Urban stormwater source control policies: why and how? | C12: Urban areas | D12: urban area | E12: Q702492 | G12: human settlement > group of structures or buildings > group of works > group > set | H12: exact_label | I12: exact_label | J12: no | K12: 100 | L12: 50 | Q12: yes | S12: =LOWER(TRIM(CLEAN(Q12))) -> yes | T12: =IF(S12="","",LOWER(TRIM(S12))) -> yes
A13: 1002652 | B13: Urban stormwater source control policies: why and how? | C13: Urban areas | D13: urban area | E13: Q702492 | G13: human settlement > group of structures or buildings > group of works > work > artificial object | H13: exact_label | I13: exact_label | J13: no | K13: 100 | L13: 50 | Q13: yes | S13: =LOWER(TRIM(CLEAN(Q13))) -> yes | T13: =IF(S13="","",LOWER(TRIM(S13))) -> yes
A14: 1002652 | B14: Urban stormwater source control policies: why and how? | C14: Urban areas | D14: urban area | E14: Q702492 | G14: human settlement > group of structures or buildings > group of works > work > cultural artifact | H14: exact_label | I14: exact_label | J14: no | K14: 100 | L14: 50 | Q14: yes | S14: =LOWER(TRIM(CLEAN(Q14))) -> yes | T14: =IF(S14="","",LOWER(TRIM(S14))) -> yes
A15: 1002652 | B15: Urban stormwater source control policies: why and how? | C15: Urban areas | D15: urban area | E15: Q702492 | G15: human settlement > group of structures or buildings > architectural structure > artificial physical structure > physical structure | H15: exact_label | I15: exact_label | J15: no | K15: 100 | L15: 50 | Q15: yes | S15: =LOWER(TRIM(CLEAN(Q15))) -> yes | T15: =IF(S15="","",LOWER(TRIM(S15))) -> yes
A16: 1002652 | B16: Urban stormwater source control policies: why and how? | C16: Urban areas | D16: urban area | E16: Q702492 | G16: human settlement > group of structures or buildings > architectural structure > artificial physical structure > artificial physical object | H16: exact_label | I16: exact_label | J16: no | K16: 100 | L16: 50 | Q16: yes | S16: =LOWER(TRIM(CLEAN(Q16))) -> yes | T16: =IF(S16="","",LOWER(TRIM(S16))) -> yes
A17: 1002652 | B17: Urban stormwater source control policies: why and how? | C17: Urban areas | D17: urban area | E17: Q702492 | G17: human settlement > group of structures or buildings > architectural structure > artificial physical structure > technical system | H17: exact_label | I17: exact_label | J17: no | K17: 100 | L17: 50 | Q17: yes | S17: =LOWER(TRIM(CLEAN(Q17))) -> yes | T17: =IF(S17="","",LOWER(TRIM(S17))) -> yes
A18: 1002652 | B18: Urban stormwater source control policies: why and how? | C18: Urban areas | D18: urban area | E18: Q702492 | G18: human settlement > group of structures or buildings > architectural structure > fixed construction > geographical feature | H18: exact_label | I18: exact_label | J18: no | K18: 100 | L18: 50 | Q18: yes | S18: =LOWER(TRIM(CLEAN(Q18))) -> yes | T18: =IF(S18="","",LOWER(TRIM(S18))) -> yes
A19: 1002652 | B19: Urban stormwater source control policies: why and how? | C19: Urban areas | D19: urban area | E19: Q702492 | G19: human settlement > group of structures or buildings > architectural structure > fixed construction > artificial physical object | H19: exact_label | I19: exact_label | J19: no | K19: 100 | L19: 50 | Q19: yes | S19: =LOWER(TRIM(CLEAN(Q19))) -> yes | T19: =IF(S19="","",LOWER(TRIM(S19))) -> yes
... A22: 1002652 | B22: Urban stormwater source control policies: why and how? | C22: Urban areas | D22: urban area | E22: Q702492 | G22: human settlement > group of structures or buildings > architectural structure > E25 Human-Made Feature > artificial physical object | H22: exact_label | I22: exact_label | J22: no | K22: 100 | L22: 50 | Q22: yes | S22: =LOWER(TRIM(CLEAN(Q22))) -> yes | T22: =IF(S22="","",LOWER(TRIM(S22))) -> yes
A23: 1002652 | B23: Urban stormwater source control policies: why and how? | C23: Source control | H23: none | I23: none | J23: yes | K23: 0 | L23: 0 | Q23: yes | S23: =LOWER(TRIM(CLEAN(Q23))) -> yes | T23: =IF(S23="","",LOWER(TRIM(S23))) -> yes
A24: 1002652 | B24: Urban stormwater source control policies: why and how? | C24: Policy-making | H24: none | I24: none | J24: no | K24: 0 | L24: 0 | Q24: yes | S24: =LOWER(TRIM(CLEAN(Q24))) -> yes | T24: =IF(S24="","",LOWER(TRIM(S24))) -> yes
A25: 1015767 | B25: Clarification about component mode synthesis methods for substructures with physical flexible interfaces | C25: Component mode synthesis | H25: none | I25: none | J25: no | K25: 0 | L25: 0 | Q25: yes | S25: =LOWER(TRIM(CLEAN(Q25))) -> yes | T25: =IF(S25="","",LOWER(TRIM(S25))) -> yes
A26: 1015767 | B26: Clarification about component mode synthesis methods for substructures with physical flexible interfaces | C26: Dynamic substructuring | D26: dynamic substructuring | E26: Q25112238 | H26: context | I26: context | J26: no | K26: 95.5 | L26: 107.3 | P26: found but no description was defined | Q26: wrong | S26: =LOWER(TRIM(CLEAN(Q26))) -> wrong | T26: =IF(S26="","",LOWER(TRIM(S26))) -> wrong
A27: 1015767 | B27: Clarification about component mode synthesis methods for substructures with physical flexible interfaces | C27: Flexible interface | H27: none | I27: none | J27: no | K27: 0 | L27: 0 | Q27: yes | S27: =LOWER(TRIM(CLEAN(Q27))) -> yes | T27: =IF(S27="","",LOWER(TRIM(S27))) -> yes
A28: 1015767 | B28: Clarification about component mode synthesis methods for substructures with physical flexible interfaces | C28: Computational mechanics | D28: computational mechanics | E28: Q919765 | G28: mechanics > physics > natural science > science > knowledge system | H28: context | I28: context | J28: no | K28: 95.7 | L28: 113.4 | Q28: yes | S28: =LOWER(TRIM(CLEAN(Q28))) -> yes | T28: =IF(S28="","",LOWER(TRIM(S28))) -> yes
A29: 1015767 | B29: Clarification about component mode synthesis methods for substructures with physical flexible interfaces | C29: Computational mechanics | D29: computational mechanics | E29: Q919765 | G29: mechanics > physics > natural science > science > knowledge | H29: context | I29: context | J29: no | K29: 95.7 | L29: 113.4 | Q29: yes | S29: =LOWER(TRIM(CLEAN(Q29))) -> yes | T29: =IF(S29="","",LOWER(TRIM(S29))) -> yes
A30: 1015767 | B30: Clarification about component mode synthesis methods for substructures with physical flexible interfaces | C30: Computational mechanics | D30: computational mechanics | E30: Q919765 | G30: mechanics > physics > natural science > science > outline of academic disciplines | H30: context | I30: context | J30: no | K30: 95.7 | L30: 113.4 | Q30: yes | S30: =LOWER(TRIM(CLEAN(Q30))) -> yes | T30: =IF(S30="","",LOWER(TRIM(S30))) -> yes
A31: 1015767 | B31: Clarification about component mode synthesis methods for substructures with physical flexible interfaces | C31: Computational mechanics | D31: computational mechanics | E31: Q919765 | G31: mechanics > physics > natural science > science > epistemology | H31: context | I31: context | J31: no | K31: 95.7 | L31: 113.4 | Q31: yes | S31: =LOWER(TRIM(CLEAN(Q31))) -> yes | T31: =IF(S31="","",LOWER(TRIM(S31))) -> yes
A32: 1015767 | B32: Clarification about component mode synthesis methods for substructures with physical flexible interfaces | C32: Computational mechanics | D32: computational mechanics | E32: Q919765 | G32: mechanics > physics > natural science > science > research | H32: context | I32: context | J32: no | K32: 95.7 | L32: 113.4 | Q32: yes | S32: =LOWER(TRIM(CLEAN(Q32))) -> yes | T32: =IF(S32="","",LOWER(TRIM(S32))) -> yes
A33: 1015767 | B33: Clarification about component mode synthesis methods for substructures with physical flexible interfaces | C33: Computational mechanics | D33: computational mechanics | E33: Q919765 | G33: mechanics > physics > natural science > science > logic | H33: context | I33: context | J33: no | K33: 95.7 | L33: 113.4 | Q33: yes | S33: =LOWER(TRIM(CLEAN(Q33))) -> yes | T33: =IF(S33="","",LOWER(TRIM(S33))) -> yes
A34: 1015767 | B34: Clarification about component mode synthesis methods for substructures with physical flexible interfaces | C34: Computational mechanics | D34: computational mechanics | E34: Q919765 | G34: mechanics > physics > natural science > science > intellectual activity | H34: context | I34: context | J34: no | K34: 95.7 | L34: 113.4 | Q34: yes | S34: =LOWER(TRIM(CLEAN(Q34))) -> yes | T34: =IF(S34="","",LOWER(TRIM(S34))) -> yes
A35: 1015767 | B35: Clarification about component mode synthesis methods for substructures with physical flexible interfaces | C35: Computational mechanics | D35: computational mechanics | E35: Q919765 | G35: mechanics > physics > physical sciences > natural science > science | H35: context | I35: context | J35: no | K35: 95.7 | L35: 113.4 | Q35: yes | S35: =LOWER(TRIM(CLEAN(Q35))) -> yes | T35: =IF(S35="","",LOWER(TRIM(S35))) -> yes
A36: 1015767 | B36: Clarification about component mode synthesis methods for substructures with physical flexible interfaces | C36: Computational mechanics | D36: computational mechanics | E36: Q919765 | G36: computational physics > computational science > applied mathematics > mathematics > natural science | H36: context | I36: context | J36: no | K36: 95.7 | L36: 113.4 | Q36: yes | S36: =LOWER(TRIM(CLEAN(Q36))) -> yes | T36: =IF(S36="","",LOWER(TRIM(S36))) -> yes
A37: 1015767 | B37: Clarification about component mode synthesis methods for substructures with physical flexible interfaces | C37: Computational mechanics | D37: computational mechanics | E37: Q919765 | G37: computational physics > computational science > computer science > formal science > exact science | H37: context | I37: context | J37: no | K37: 95.7 | L37: 113.4 | Q37: yes | S37: =LOWER(TRIM(CLEAN(Q37))) -> yes | T37: =IF(S37="","",LOWER(TRIM(S37))) -> yes
A38: 1015767 | B38: Clarification about component mode synthesis methods for substructures with physical flexible interfaces | C38: Computational mechanics | D38: computational mechanics | E38: Q919765 | G38: computational physics > physics > natural science > science > knowledge system | H38: context | I38: context | J38: no | K38: 95.7 | L38: 113.4 | Q38: yes | S38: =LOWER(TRIM(CLEAN(Q38))) -> yes | T38: =IF(S38="","",LOWER(TRIM(S38))) -> yes
A39: 1015767 | B39: Clarification about component mode synthesis methods for substructures with physical flexible interfaces | C39: Computational mechanics | D39: computational mechanics | E39: Q919765 | G39: computational physics > physics > natural science > science > knowledge | H39: context | I39: context | J39: no | K39: 95.7 | L39: 113.4 | Q39: yes | S39: =LOWER(TRIM(CLEAN(Q39))) -> yes | T39: =IF(S39="","",LOWER(TRIM(S39))) -> yes
... A45: 1015767 | B45: Clarification about component mode synthesis methods for substructures with physical flexible interfaces | C45: Computational mechanics | D45: computational mechanics | E45: Q919765 | G45: computational physics > physics > physical sciences > natural science > science | H45: context | I45: context | J45: no | K45: 95.7 | L45: 113.4 | Q45: yes | S45: =LOWER(TRIM(CLEAN(Q45))) -> yes | T45: =IF(S45="","",LOWER(TRIM(S45))) -> yes
A46: 1061949 | B46: Reduced-order model for the dynamical analysis of complex structures with a high modal density | C46: Reduced-order model | H46: none | I46: none | J46: no | K46: 0 | L46: 0 | Q46: yes | S46: =LOWER(TRIM(CLEAN(Q46))) -> yes | T46: =IF(S46="","",LOWER(TRIM(S46))) -> yes
A47: 1061949 | B47: Reduced-order model for the dynamical analysis of complex structures with a high modal density | C47: Structural dynamics | D47: structural dynamics | E47: Q811197 | G47: structural analysis > analysis > inquiry > seeking > activity | H47: exact_label | I47: exact_label | J47: no | K47: 100 | L47: 80 | M47: Q11862829 | N47: academic discipline | Q47: yes | S47: =LOWER(TRIM(CLEAN(Q47))) -> yes | T47: =IF(S47="","",LOWER(TRIM(S47))) -> yes
A48: 1061949 | B48: Reduced-order model for the dynamical analysis of complex structures with a high modal density | C48: Structural dynamics | D48: structural dynamics | E48: Q811197 | G48: structural analysis > analysis > inquiry > planned process > process | H48: exact_label | I48: exact_label | J48: no | K48: 100 | L48: 80 | M48: Q11862829 | N48: academic discipline | Q48: yes | S48: =LOWER(TRIM(CLEAN(Q48))) -> yes | T48: =IF(S48="","",LOWER(TRIM(S48))) -> yes
A49: 1061949 | B49: Reduced-order model for the dynamical analysis of complex structures with a high modal density | C49: Structural dynamics | D49: structural dynamics | E49: Q811197 | G49: structural analysis > analysis > inquiry > planned process > intentional human activity | H49: exact_label | I49: exact_label | J49: no | K49: 100 | L49: 80 | M49: Q11862829 | N49: academic discipline | Q49: yes | S49: =LOWER(TRIM(CLEAN(Q49))) -> yes | T49: =IF(S49="","",LOWER(TRIM(S49))) -> yes
A50: 1061949 | B50: Reduced-order model for the dynamical analysis of complex structures with a high modal density | C50: Structural dynamics | D50: structural dynamics | E50: Q811197 | G50: structural analysis > analysis > scholarly method > method > means | H50: exact_label | I50: exact_label | J50: no | K50: 100 | L50: 80 | M50: Q11862829 | N50: academic discipline | Q50: yes | S50: =LOWER(TRIM(CLEAN(Q50))) -> yes | T50: =IF(S50="","",LOWER(TRIM(S50))) -> yes
A51: 1061949 | B51: Reduced-order model for the dynamical analysis of complex structures with a high modal density | C51: High modal density | H51: none | I51: none | J51: no | K51: 0 | L51: 0 | Q51: yes | S51: =LOWER(TRIM(CLEAN(Q51))) -> yes | T51: =IF(S51="","",LOWER(TRIM(S51))) -> yes
A52: 1061949 | B52: Reduced-order model for the dynamical analysis of complex structures with a high modal density | C52: ROM | D52: Rom | E52: Q3440554 | H52: exact_label | I52: exact_label | J52: no | K52: 100 | L52: 50 | M52: Q830038 | N52: Ferengi | Q52: wrong | S52: =LOWER(TRIM(CLEAN(Q52))) -> wrong | T52: =IF(S52="","",LOWER(TRIM(S52))) -> wrong
A53: 1064345 | B53: Modelling the time fluctuation of indoor air formaldehyde concentrations: variability structure identification and forecasting using non linear models | C53: Formaldehyde | D53: Formaldehyde | E53: Q14922294 | H53: context | I53: context | J53: no | K53: 100 | L53: 112 | M53: Q134556 | N53: single | Q53: wrong | S53: =LOWER(TRIM(CLEAN(Q53))) -> wrong | T53: =IF(S53="","",LOWER(TRIM(S53))) -> wrong
A54: 1064345 | B54: Modelling the time fluctuation of indoor air formaldehyde concentrations: variability structure identification and forecasting using non linear models | C54: Clustering | D54: clustering | E54: Q5136710 | H54: context | I54: context | J54: no | K54: 90 | L54: 105 | P54: seen not related. description not defined | Q54: wrong | S54: =LOWER(TRIM(CLEAN(Q54))) -> wrong | T54: =IF(S54="","",LOWER(TRIM(S54))) -> wrong
A55: 1064345 | B55: Modelling the time fluctuation of indoor air formaldehyde concentrations: variability structure identification and forecasting using non linear models | C55: Forecasting | D55: Forecasting | E55: Q49297242 | H55: context | I55: context | J55: no | K55: 100 | L55: 112 | M55: Q3305213 | N55: painting | P55: painting | Q55: wrong | S55: =LOWER(TRIM(CLEAN(Q55))) -> wrong | T55: =IF(S55="","",LOWER(TRIM(S55))) -> wrong
A56: 1064345 | B56: Modelling the time fluctuation of indoor air formaldehyde concentrations: variability structure identification and forecasting using non linear models | C56: SOTA | D56: SOTA | E56: Q11243978 | H56: context | I56: context | J56: no | K56: 100 | L56: 110 | M56: Q5 | N56: human | Q56: wrong | S56: =LOWER(TRIM(CLEAN(Q56))) -> wrong | T56: =IF(S56="","",LOWER(TRIM(S56))) -> wrong
A57: 1064345 | B57: Modelling the time fluctuation of indoor air formaldehyde concentrations: variability structure identification and forecasting using non linear models | C57: SETAR | D57: SETAR | E57: Q7456351 | H57: context | I57: context | J57: no | K57: 100 | L57: 112 | M57: Q4830453;Q6881511 | N57: business;enterprise | P57: seen not related | Q57: wrong | S57: =LOWER(TRIM(CLEAN(Q57))) -> wrong | T57: =IF(S57="","",LOWER(TRIM(S57))) -> wrong
A58: 1068317 | B58: Analysis of dissociated dislocations in a deformed bicrystal close to the rhombohedral twin orientation in -alumina | C58: Grain boundary | D58: Grain boundary | E58: Q1605670 | H58: context | I58: context | J58: no | K58: 100 | L58: 110 | P58: seen no description defined | Q58: wrong | S58: =LOWER(TRIM(CLEAN(Q58))) -> wrong | T58: =IF(S58="","",LOWER(TRIM(S58))) -> wrong
A59: 1068317 | B59: Analysis of dissociated dislocations in a deformed bicrystal close to the rhombohedral twin orientation in -alumina | C59: Alumina | D59: Aluminaut | E59: Q447411 | H59: context | I59: context | J59: no | K59: 87.5 | L59: 52.5 | M59: Q11446;Q130326199 | N59: ship;preserved watercraft | P59: seen but not related | Q59: wrong | S59: =LOWER(TRIM(CLEAN(Q59))) -> wrong | T59: =IF(S59="","",LOWER(TRIM(S59))) -> wrong
A60: 1068317 | B60: Analysis of dissociated dislocations in a deformed bicrystal close to the rhombohedral twin orientation in -alumina | C60: Bicrystal | H60: none | I60: none | J60: no | K60: 0 | L60: 0 | Q60: yes | S60: =LOWER(TRIM(CLEAN(Q60))) -> yes | T60: =IF(S60="","",LOWER(TRIM(S60))) -> yes
A61: 1068317 | B61: Analysis of dissociated dislocations in a deformed bicrystal close to the rhombohedral twin orientation in -alumina | C61: Plasticity | D61: plasticity | E61: Q1230210 | G61: possibility > quality > property > abstract entity > entity | H61: context | I61: context | J61: no | K61: 90 | L61: 111 | P61: seen and might be but could not verify the levels | Q61: yes | S61: =LOWER(TRIM(CLEAN(Q61))) -> yes | T61: =IF(S61="","",LOWER(TRIM(S61))) -> yes
A62: 1068317 | B62: Analysis of dissociated dislocations in a deformed bicrystal close to the rhombohedral twin orientation in -alumina | C62: Plasticity | D62: plasticity | E62: Q1230210 | G62: possibility > state > phenomenon > occurrent > entity | H62: context | I62: context | J62: no | K62: 90 | L62: 111 | Q62: yes | S62: =LOWER(TRIM(CLEAN(Q62))) -> yes | T62: =IF(S62="","",LOWER(TRIM(S62))) -> yes
A63: 1068317 | B63: Analysis of dissociated dislocations in a deformed bicrystal close to the rhombohedral twin orientation in -alumina | C63: Plasticity | D63: plasticity | E63: Q1230210 | G63: possibility > state > phenomenon > observable entity > entity | H63: context | I63: context | J63: no | K63: 90 | L63: 111 | Q63: yes | S63: =LOWER(TRIM(CLEAN(Q63))) -> yes | T63: =IF(S63="","",LOWER(TRIM(S63))) -> yes
A64: 1068317 | B64: Analysis of dissociated dislocations in a deformed bicrystal close to the rhombohedral twin orientation in -alumina | C64: Plasticity | D64: plasticity | E64: Q1230210 | G64: possibility > state > property > abstract entity > entity | H64: context | I64: context | J64: no | K64: 90 | L64: 111 | Q64: yes | S64: =LOWER(TRIM(CLEAN(Q64))) -> yes | T64: =IF(S64="","",LOWER(TRIM(S64))) -> yes
A65: 1068317 | B65: Analysis of dissociated dislocations in a deformed bicrystal close to the rhombohedral twin orientation in -alumina | C65: Dislocations | D65: Dislocations | E65: Q110893377 | H65: context | I65: context | J65: no | K65: 100 | L65: 113 | M65: Q1656682;Q667276 | N65: event;art exhibition | Q65: wrong | S65: =LOWER(TRIM(CLEAN(Q65))) -> wrong | T65: =IF(S65="","",LOWER(TRIM(S65))) -> wrong
A66: 1068317 | B66: Analysis of dissociated dislocations in a deformed bicrystal close to the rhombohedral twin orientation in -alumina | C66: Dissociation | D66: Dissociation | E66: Q27813879 | H66: context | I66: context | J66: no | K66: 100 | L66: 112 | M66: Q482994 | N66: album | P66: seen not related | Q66: wrong | S66: =LOWER(TRIM(CLEAN(Q66))) -> wrong | T66: =IF(S66="","",LOWER(TRIM(S66))) -> wrong
A67: 1068317 | B67: Analysis of dissociated dislocations in a deformed bicrystal close to the rhombohedral twin orientation in -alumina | C67: Transmission electron microscopy | D67: transmission electron microscopy | E67: Q110779037 | G67: electron microscopy > microscopy > technique > method > means | H67: exact_label | I67: exact_label | J67: no | K67: 100 | L67: 50 | Q67: yes | S67: =LOWER(TRIM(CLEAN(Q67))) -> yes | T67: =IF(S67="","",LOWER(TRIM(S67))) -> yes
A68: 1068317 | B68: Analysis of dissociated dislocations in a deformed bicrystal close to the rhombohedral twin orientation in -alumina | C68: Transmission electron microscopy | D68: transmission electron microscopy | E68: Q110779037 | G68: electron microscopy > microscopy > technique > activity > process | H68: exact_label | I68: exact_label | J68: no | K68: 100 | L68: 50 | Q68: yes | S68: =LOWER(TRIM(CLEAN(Q68))) -> yes | T68: =IF(S68="","",LOWER(TRIM(S68))) -> yes
A69: 1068317 | B69: Analysis of dissociated dislocations in a deformed bicrystal close to the rhombohedral twin orientation in -alumina | C69: Transmission electron microscopy | D69: transmission electron microscopy | E69: Q110779037 | G69: electron microscopy > microscopy > analysis > inquiry > seeking | H69: exact_label | I69: exact_label | J69: no | K69: 100 | L69: 50 | Q69: yes | S69: =LOWER(TRIM(CLEAN(Q69))) -> yes | T69: =IF(S69="","",LOWER(TRIM(S69))) -> yes
A70: 1068317 | B70: Analysis of dissociated dislocations in a deformed bicrystal close to the rhombohedral twin orientation in -alumina | C70: Transmission electron microscopy | D70: transmission electron microscopy | E70: Q110779037 | G70: electron microscopy > microscopy > analysis > inquiry > planned process | H70: exact_label | I70: exact_label | J70: no | K70: 100 | L70: 50 | Q70: yes | S70: =LOWER(TRIM(CLEAN(Q70))) -> yes | T70: =IF(S70="","",LOWER(TRIM(S70))) -> yes
A71: 1068317 | B71: Analysis of dissociated dislocations in a deformed bicrystal close to the rhombohedral twin orientation in -alumina | C71: Transmission electron microscopy | D71: transmission electron microscopy | E71: Q110779037 | G71: electron microscopy > microscopy > analysis > scholarly method > method | H71: exact_label | I71: exact_label | J71: no | K71: 100 | L71: 50 | Q71: yes | S71: =LOWER(TRIM(CLEAN(Q71))) -> yes | T71: =IF(S71="","",LOWER(TRIM(S71))) -> yes
A72: 1068317 | B72: Analysis of dissociated dislocations in a deformed bicrystal close to the rhombohedral twin orientation in -alumina | C72: Transmission electron microscopy | D72: transmission electron microscopy | E72: Q110779037 | G72: electron microscopy > microscopy > scientific technique > technique > method | H72: exact_label | I72: exact_label | J72: no | K72: 100 | L72: 50 | Q72: yes | S72: =LOWER(TRIM(CLEAN(Q72))) -> yes | T72: =IF(S72="","",LOWER(TRIM(S72))) -> yes
A73: 1068317 | B73: Analysis of dissociated dislocations in a deformed bicrystal close to the rhombohedral twin orientation in -alumina | C73: Transmission electron microscopy | D73: transmission electron microscopy | E73: Q110779037 | G73: electron microscopy > microscopy > scientific technique > technique > activity | H73: exact_label | I73: exact_label | J73: no | K73: 100 | L73: 50 | Q73: yes | S73: =LOWER(TRIM(CLEAN(Q73))) -> yes | T73: =IF(S73="","",LOWER(TRIM(S73))) -> yes
A74: 1081822 | B74: A history of basin inversion, scarp retreat and shallow denudation: The Araripe basin as a keystone for understanding long-term landscape evolution in NE Brazil | C74: Palaeolandforms | H74: none | I74: none | J74: no | K74: 0 | L74: 0 | Q74: yes | S74: =LOWER(TRIM(CLEAN(Q74))) -> yes | T74: =IF(S74="","",LOWER(TRIM(S74))) -> yes
A75: 1081822 | B75: A history of basin inversion, scarp retreat and shallow denudation: The Araripe basin as a keystone for understanding long-term landscape evolution in NE Brazil | C75: Topographic inversion | H75: none | I75: none | J75: no | K75: 0 | L75: 0 | Q75: yes | S75: =LOWER(TRIM(CLEAN(Q75))) -> yes | T75: =IF(S75="","",LOWER(TRIM(S75))) -> yes
A76: 1081822 | B76: A history of basin inversion, scarp retreat and shallow denudation: The Araripe basin as a keystone for understanding long-term landscape evolution in NE Brazil | C76: Denudation history | H76: none | I76: none | J76: no | K76: 0 | L76: 0 | Q76: yes | S76: =LOWER(TRIM(CLEAN(Q76))) -> yes | T76: =IF(S76="","",LOWER(TRIM(S76))) -> yes
A77: 1081822 | B77: A history of basin inversion, scarp retreat and shallow denudation: The Araripe basin as a keystone for understanding long-term landscape evolution in NE Brazil | C77: Soil distribution | H77: none | I77: none | J77: no | K77: 0 | L77: 0 | Q77: yes | S77: =LOWER(TRIM(CLEAN(Q77))) -> yes | T77: =IF(S77="","",LOWER(TRIM(S77))) -> yes
A78: 1081822 | B78: A history of basin inversion, scarp retreat and shallow denudation: The Araripe basin as a keystone for understanding long-term landscape evolution in NE Brazil | C78: Scarp retreat | D78: scarp retreat | E78: Q7430497 | H78: exact_label | I78: exact_label | J78: no | K78: 100 | L78: 50 | M78: Q10928429 | N78: geological process | Q78: yes | S78: =LOWER(TRIM(CLEAN(Q78))) -> yes | T78: =IF(S78="","",LOWER(TRIM(S78))) -> yes
A79: 1081825 | B79: Late Cenozoic and present-day hillslope erosion dynamics in a passive margin context: stability or instability? Case studies in Northeast Brazil | C79: Tropical geomorphology | H79: none | I79: none | J79: no | K79: 0 | L79: 0 | Q79: yes | S79: =LOWER(TRIM(CLEAN(Q79))) -> yes | T79: =IF(S79="","",LOWER(TRIM(S79))) -> yes
A80: 1081825 | B80: Late Cenozoic and present-day hillslope erosion dynamics in a passive margin context: stability or instability? Case studies in Northeast Brazil | C80: Backwearing | H80: none | I80: none | J80: no | K80: 0 | L80: 0 | Q80: yes | S80: =LOWER(TRIM(CLEAN(Q80))) -> yes | T80: =IF(S80="","",LOWER(TRIM(S80))) -> yes
A81: 1081825 | B81: Late Cenozoic and present-day hillslope erosion dynamics in a passive margin context: stability or instability? Case studies in Northeast Brazil | C81: Hillslope landforms and processes | H81: none | I81: none | J81: no | K81: 0 | L81: 0 | Q81: yes | S81: =LOWER(TRIM(CLEAN(Q81))) -> yes | T81: =IF(S81="","",LOWER(TRIM(S81))) -> yes
A82: 1081825 | B82: Late Cenozoic and present-day hillslope erosion dynamics in a passive margin context: stability or instability? Case studies in Northeast Brazil | C82: Brazil | D82: Brazil | E82: Q155 | F82: 11868637v | H82: context | I82: context | J82: no | K82: 100 | L82: 112 | M82: Q3624078;Q512187;Q6256;Q859563 | N82: secular state;sovereign state;federal republic;country | Q82: yes | S82: =LOWER(TRIM(CLEAN(Q82))) -> yes | T82: =IF(S82="","",LOWER(TRIM(S82))) -> yes
A83: 1081825 | B83: Late Cenozoic and present-day hillslope erosion dynamics in a passive margin context: stability or instability? Case studies in Northeast Brazil | C83: Morphological resistance | H83: none | I83: none | J83: no | K83: 0 | L83: 0 | Q83: yes | S83: =LOWER(TRIM(CLEAN(Q83))) -> yes | T83: =IF(S83="","",LOWER(TRIM(S83))) -> yes
A84: 1081825 | B84: Late Cenozoic and present-day hillslope erosion dynamics in a passive margin context: stability or instability? Case studies in Northeast Brazil | C84: Downwearing | H84: none | I84: none | J84: no | K84: 0 | L84: 0 | Q84: yes | S84: =LOWER(TRIM(CLEAN(Q84))) -> yes | T84: =IF(S84="","",LOWER(TRIM(S84))) -> yes
A85: 1081825 | B85: Late Cenozoic and present-day hillslope erosion dynamics in a passive margin context: stability or instability? Case studies in Northeast Brazil | C85: Mass wasting | D85: mass wasting | E85: Q1567542 | G85: motion > physical process > physicochemical process > process > occurrent | H85: context | I85: context | J85: no | K85: 91.7 | L85: 111 | Q85: yes | S85: =LOWER(TRIM(CLEAN(Q85))) -> yes | T85: =IF(S85="","",LOWER(TRIM(S85))) -> yes
A86: 1081825 | B86: Late Cenozoic and present-day hillslope erosion dynamics in a passive margin context: stability or instability? Case studies in Northeast Brazil | C86: Mass wasting | D86: mass wasting | E86: Q1567542 | G86: motion > physical process > physicochemical process > process > sequence | H86: context | I86: context | J86: no | K86: 91.7 | L86: 111 | Q86: yes | S86: =LOWER(TRIM(CLEAN(Q86))) -> yes | T86: =IF(S86="","",LOWER(TRIM(S86))) -> yes
A87: 1081825 | B87: Late Cenozoic and present-day hillslope erosion dynamics in a passive margin context: stability or instability? Case studies in Northeast Brazil | C87: Mass wasting | D87: mass wasting | E87: Q1567542 | G87: motion > physical process > physical phenomenon > phenomenon > occurrent | H87: context | I87: context | J87: no | K87: 91.7 | L87: 111 | Q87: yes | S87: =LOWER(TRIM(CLEAN(Q87))) -> yes | T87: =IF(S87="","",LOWER(TRIM(S87))) -> yes
A88: 1081825 | B88: Late Cenozoic and present-day hillslope erosion dynamics in a passive margin context: stability or instability? Case studies in Northeast Brazil | C88: Mass wasting | D88: mass wasting | E88: Q1567542 | G88: motion > physical process > physical phenomenon > phenomenon > observable entity | H88: context | I88: context | J88: no | K88: 91.7 | L88: 111 | Q88: yes | S88: =LOWER(TRIM(CLEAN(Q88))) -> yes | T88: =IF(S88="","",LOWER(TRIM(S88))) -> yes
A89: 1081825 | B89: Late Cenozoic and present-day hillslope erosion dynamics in a passive margin context: stability or instability? Case studies in Northeast Brazil | C89: Mass wasting | D89: mass wasting | E89: Q1567542 | G89: motion > change > occurrent > entity > entity | H89: context | I89: context | J89: no | K89: 91.7 | L89: 111 | Q89: yes | S89: =LOWER(TRIM(CLEAN(Q89))) -> yes | T89: =IF(S89="","",LOWER(TRIM(S89))) -> yes
A90: 1082459 | B90: Landforms and neotectonics in the equatorial passive margin of Brazil | C90: Fault scarp | D90: fault scarp | E90: Q475080 | G90: landform > geomorphological unit > natural geographic object > geographical feature > geographic entity | H90: context | I90: context | J90: no | K90: 90.9 | L90: 113.5 | Q90: yes | S90: =LOWER(TRIM(CLEAN(Q90))) -> yes | T90: =IF(S90="","",LOWER(TRIM(S90))) -> yes
A91: 1082459 | B91: Landforms and neotectonics in the equatorial passive margin of Brazil | C91: Fault scarp | D91: fault scarp | E91: Q475080 | G91: landform > geomorphological unit > natural geographic object > geographical feature > concrete object | H91: context | I91: context | J91: no | K91: 90.9 | L91: 113.5 | Q91: yes | S91: =LOWER(TRIM(CLEAN(Q91))) -> yes | T91: =IF(S91="","",LOWER(TRIM(S91))) -> yes
A92: 1082459 | B92: Landforms and neotectonics in the equatorial passive margin of Brazil | C92: Fault scarp | D92: fault scarp | E92: Q475080 | G92: landform > geomorphological unit > natural geographic object > geographical feature > physical location | H92: context | I92: context | J92: no | K92: 90.9 | L92: 113.5 | Q92: yes | S92: =LOWER(TRIM(CLEAN(Q92))) -> yes | T92: =IF(S92="","",LOWER(TRIM(S92))) -> yes
A93: 1082459 | B93: Landforms and neotectonics in the equatorial passive margin of Brazil | C93: Fault scarp | D93: fault scarp | E93: Q475080 | G93: landform > geomorphological unit > natural geographic object > natural physical object > physical object | H93: context | I93: context | J93: no | K93: 90.9 | L93: 113.5 | Q93: yes | S93: =LOWER(TRIM(CLEAN(Q93))) -> yes | T93: =IF(S93="","",LOWER(TRIM(S93))) -> yes
A94: 1082459 | B94: Landforms and neotectonics in the equatorial passive margin of Brazil | C94: Fault scarp | D94: fault scarp | E94: Q475080 | G94: landform > geomorphological unit > natural geographic object > natural physical object > natural object | H94: context | I94: context | J94: no | K94: 90.9 | L94: 113.5 | Q94: yes | S94: =LOWER(TRIM(CLEAN(Q94))) -> yes | T94: =IF(S94="","",LOWER(TRIM(S94))) -> yes
A95: 1082459 | B95: Landforms and neotectonics in the equatorial passive margin of Brazil | C95: Fault scarp | D95: fault scarp | E95: Q475080 | G95: landform > geomorphological unit > natural geographic object > natural geographic entity > geographic entity | H95: context | I95: context | J95: no | K95: 90.9 | L95: 113.5 | Q95: yes | S95: =LOWER(TRIM(CLEAN(Q95))) -> yes | T95: =IF(S95="","",LOWER(TRIM(S95))) -> yes
A96: 1082459 | B96: Landforms and neotectonics in the equatorial passive margin of Brazil | C96: Fault scarp | D96: fault scarp | E96: Q475080 | G96: landform > geomorphological unit > natural geographic object > astronomical body part > fiat object part | H96: context | I96: context | J96: no | K96: 90.9 | L96: 113.5 | Q96: yes | S96: =LOWER(TRIM(CLEAN(Q96))) -> yes | T96: =IF(S96="","",LOWER(TRIM(S96))) -> yes
... A114: 1082459 | B114: Landforms and neotectonics in the equatorial passive margin of Brazil | C114: Fault scarp | D114: fault scarp | E114: Q475080 | G114: geologic feature > quality > property > abstract entity > entity | H114: context | I114: context | J114: no | K114: 90.9 | L114: 113.5 | Q114: yes | S114: =LOWER(TRIM(CLEAN(Q114))) -> yes | T114: =IF(S114="","",LOWER(TRIM(S114))) -> yes
A115: 1082459 | B115: Landforms and neotectonics in the equatorial passive margin of Brazil | C115: Neotectonics | D115: neotectonics | E115: Q2497922 | G115: tectonics > dynamic geology > physical geology > geology > natural science | H115: context | I115: context | J115: no | K115: 91.7 | L115: 114 | M115: Q87058424 | N115: branch of geology | P115: geology | Q115: yes | S115: =LOWER(TRIM(CLEAN(Q115))) -> yes | T115: =IF(S115="","",LOWER(TRIM(S115))) -> yes
A116: 1082459 | B116: Landforms and neotectonics in the equatorial passive margin of Brazil | C116: Neotectonics | D116: neotectonics | E116: Q2497922 | G116: tectonics > dynamic geology > physical geology > geology > Earth science | H116: context | I116: context | J116: no | K116: 91.7 | L116: 114 | M116: Q87058424 | N116: branch of geology | Q116: yes | S116: =LOWER(TRIM(CLEAN(Q116))) -> yes | T116: =IF(S116="","",LOWER(TRIM(S116))) -> yes
A117: 1082459 | B117: Landforms and neotectonics in the equatorial passive margin of Brazil | C117: Neotectonics | D117: neotectonics | E117: Q2497922 | G117: tectonics > dynamic geology > geophysics > physics > natural science | H117: context | I117: context | J117: no | K117: 91.7 | L117: 114 | M117: Q87058424 | N117: branch of geology | Q117: yes | S117: =LOWER(TRIM(CLEAN(Q117))) -> yes | T117: =IF(S117="","",LOWER(TRIM(S117))) -> yes
A118: 1082459 | B118: Landforms and neotectonics in the equatorial passive margin of Brazil | C118: Neotectonics | D118: neotectonics | E118: Q2497922 | G118: tectonics > dynamic geology > geophysics > physics > physical sciences | H118: context | I118: context | J118: no | K118: 91.7 | L118: 114 | M118: Q87058424 | N118: branch of geology | Q118: yes | S118: =LOWER(TRIM(CLEAN(Q118))) -> yes | T118: =IF(S118="","",LOWER(TRIM(S118))) -> yes
A119: 1082459 | B119: Landforms and neotectonics in the equatorial passive margin of Brazil | C119: Neotectonics | D119: neotectonics | E119: Q2497922 | G119: tectonics > dynamic geology > geophysics > planetary science > space sciences | H119: context | I119: context | J119: no | K119: 91.7 | L119: 114 | M119: Q87058424 | N119: branch of geology | P119: geology | Q119: yes | S119: =LOWER(TRIM(CLEAN(Q119))) -> yes | T119: =IF(S119="","",LOWER(TRIM(S119))) -> yes
A120: 1082459 | B120: Landforms and neotectonics in the equatorial passive margin of Brazil | C120: Passive margin | D120: passive margin | E120: Q1918464 | G120: zone > part > entity | H120: exact_label | I120: exact_label | J120: no | K120: 100 | L120: 50 | P120: geology/geography | Q120: yes | S120: =LOWER(TRIM(CLEAN(Q120))) -> yes | T120: =IF(S120="","",LOWER(TRIM(S120))) -> yes
A121: 1082459 | B121: Landforms and neotectonics in the equatorial passive margin of Brazil | C121: Passive margin | D121: passive margin | E121: Q1918464 | G121: zone > geographic location > geographic entity > geolocatable entity > material entity | H121: exact_label | I121: exact_label | J121: no | K121: 100 | L121: 50 | Q121: yes | S121: =LOWER(TRIM(CLEAN(Q121))) -> yes | T121: =IF(S121="","",LOWER(TRIM(S121))) -> yes
A122: 1082459 | B122: Landforms and neotectonics in the equatorial passive margin of Brazil | C122: Passive margin | D122: passive margin | E122: Q1918464 | G122: zone > geographic location > geographic entity > geolocatable entity > concrete object | H122: exact_label | I122: exact_label | J122: no | K122: 100 | L122: 50 | Q122: yes | S122: =LOWER(TRIM(CLEAN(Q122))) -> yes | T122: =IF(S122="","",LOWER(TRIM(S122))) -> yes
A123: 1082459 | B123: Landforms and neotectonics in the equatorial passive margin of Brazil | C123: Passive margin | D123: passive margin | E123: Q1918464 | G123: zone > geographic location > geographic entity > geolocatable entity > occurrence | H123: exact_label | I123: exact_label | J123: no | K123: 100 | L123: 50 | Q123: yes | S123: =LOWER(TRIM(CLEAN(Q123))) -> yes | T123: =IF(S123="","",LOWER(TRIM(S123))) -> yes
A124: 1082459 | B124: Landforms and neotectonics in the equatorial passive margin of Brazil | C124: Passive margin | D124: passive margin | E124: Q1918464 | G124: zone > geographic location > geographic entity > region of space > spacetime region | H124: exact_label | I124: exact_label | J124: no | K124: 100 | L124: 50 | Q124: yes | S124: =LOWER(TRIM(CLEAN(Q124))) -> yes | T124: =IF(S124="","",LOWER(TRIM(S124))) -> yes
...

Sheet Wikidata_upec_civil_20_part2
A1: docid | B1: title | C1: keyword | D1: wikidata_label | E1: wikidata_qid | F1: bnf_id | G1: p279_path | H1: retry_source | I1: match_stage | J1: is_disambiguation | K1: label_similarity | L1: match_score | M1: p31_types | N1: p31_label | O1: wikidata matched | P1: bnf matched | Q1: remarks | R1: % QID matched | S1: % BnF matched | U1: keywords | V1: # of KEYWORDS
A2: 1131185 | B2: Les Â« riviÃ¨res de pierres Â» : une formation en marge des catÃ©gories classiques. Questions posÃ©es dans le cas du massif du MÃ©zenc (Velay oriental, Sud-Est du Massif central, France). | C2: French Massif central | H2: none | I2: none | J2: no | K2: 0 | L2: 0 | O2: YES | P2: YES | R2: =COUNTIF(O2:O39,"*YES*")/COUNTA(O2:O39) -> 0.92105263 | S2: =COUNTIF(P2:P39,"*YES*")/COUNTA(P2:P39) -> 0.92105263 | U2: {=_xlfn.UNIQUE(C2:C192)} -> French Massif central | V2: =COUNTIF(C2:C192, U2) -> 1 | X2: Unique Keywords | Y2: {=COUNTA(_xlfn.UNIQUE(_xlfn._xlws.FILTER(C2:C192,C2:C192<>"")))} -> 48
A3: 1131185 | B3: Les Â« riviÃ¨res de pierres Â» : une formation en marge des catÃ©gories classiques. Questions posÃ©es dans le cas du massif du MÃ©zenc (Velay oriental, Sud-Est du Massif central, France). | C3: Blockstream | D3: Blockstream | E3: Q24909896 | H3: context | I3: context | J3: no | K3: 100 | L3: 110 | M3: Q167037 | N3: corporation | O3: NO | P3: NO | Q3: mismatched on the context | U3: Blockstream | V3: =COUNTIF(C3:C193, U3) -> 1 | X3: Unique QID | Y3: {=COUNTA(_xlfn.UNIQUE(_xlfn._xlws.FILTER(E2:E192,(E2:E192<>"")*(E2:E192<>"none"))))} -> 17
A4: 1131185 | B4: Les Â« riviÃ¨res de pierres Â» : une formation en marge des catÃ©gories classiques. Questions posÃ©es dans le cas du massif du MÃ©zenc (Velay oriental, Sud-Est du Massif central, France). | C4: Rock glacier | D4: rock glacier | E4: Q884736 | F4: 13507719g | G4: glacier > ice cover > body of water > region > geographical feature | H4: exact_label | I4: exact_label | J4: no | K4: 100 | L4: 50 | O4: YES | P4: YES | U4: Rock glacier | V4: =COUNTIF(C4:C194, U4) -> 29 | X4: % QID (vs unique keywords) | Y4: {=COUNTA(_xlfn.UNIQUE(_xlfn._xlws.FILTER(E2:E192,(E2:E192<>"")*(E2:E192<>"none")))) / COUNTA(_xlfn.UNIQUE(_xlfn._xlws.FILTER(C2:C192,C2:C192<>"")))} -> 0.35416667
A5: 1131185 | B5: Les Â« riviÃ¨res de pierres Â» : une formation en marge des catÃ©gories classiques. Questions posÃ©es dans le cas du massif du MÃ©zenc (Velay oriental, Sud-Est du Massif central, France). | C5: Rock glacier | D5: rock glacier | E5: Q884736 | F5: 13507719g | G5: glacier > ice cover > body of water > physico-geographical object > geographical feature | H5: exact_label | I5: exact_label | J5: no | K5: 100 | L5: 50 | O5: YES | P5: YES | U5: Periglacial morphology and process | V5: =COUNTIF(C5:C195, U5) -> 1 | X5: Unique BnF | Y5: {=COUNTA(_xlfn.UNIQUE(_xlfn._xlws.FILTER(F2:F192,(F2:F192<>"")*(F2:F192<>"none"))))} -> 2
A6: 1131185 | B6: Les Â« riviÃ¨res de pierres Â» : une formation en marge des catÃ©gories classiques. Questions posÃ©es dans le cas du massif du MÃ©zenc (Velay oriental, Sud-Est du Massif central, France). | C6: Rock glacier | D6: rock glacier | E6: Q884736 | F6: 13507719g | G6: glacier > ice cover > body of water > physico-geographical object > physical object | H6: exact_label | I6: exact_label | J6: no | K6: 100 | L6: 50 | O6: YES | P6: YES | U6: Pleistocene | V6: =COUNTIF(C6:C196, U6) -> 1 | X6: %BnF ID (vs unique keywords) | Y6: {=COUNTA(_xlfn.UNIQUE(_xlfn._xlws.FILTER(E2:F192,(F2:F192<>"")*(F2:F192<>"none")))) / COUNTA(_xlfn.UNIQUE(_xlfn._xlws.FILTER(C2:C192,C2:C192<>"")))} -> 0.083333333
A7: 1131185 | B7: Les Â« riviÃ¨res de pierres Â» : une formation en marge des catÃ©gories classiques. Questions posÃ©es dans le cas du massif du MÃ©zenc (Velay oriental, Sud-Est du Massif central, France). | C7: Rock glacier | D7: rock glacier | E7: Q884736 | F7: 13507719g | G7: glacier > ice cover > body of water > habitat > region | H7: exact_label | I7: exact_label | J7: no | K7: 100 | L7: 50 | O7: YES | P7: YES | U7: Late Glacial | V7: =COUNTIF(C7:C197, U7) -> 1 | X7: %QID matched | Y7: =COUNTIF(O2:O192,"*YES*")/COUNTA(O2:O192) -> 0.95811518
A8: 1131185 | B8: Les Â« riviÃ¨res de pierres Â» : une formation en marge des catÃ©gories classiques. Questions posÃ©es dans le cas du massif du MÃ©zenc (Velay oriental, Sud-Est du Massif central, France). | C8: Rock glacier | D8: rock glacier | E8: Q884736 | F8: 13507719g | G8: glacier > ice cover > body of water > habitat > natural environment | H8: exact_label | I8: exact_label | J8: no | K8: 100 | L8: 50 | O8: YES | P8: YES | U8: Eastern Velay | V8: =COUNTIF(C8:C198, U8) -> 1 | X8: %BnF matched | Y8: =COUNTIF(P2:P192,"*YES*")/COUNTA(P2:P192) -> 0.98113208
A9: 1131185 | B9: Les Â« riviÃ¨res de pierres Â» : une formation en marge des catÃ©gories classiques. Questions posÃ©es dans le cas du massif du MÃ©zenc (Velay oriental, Sud-Est du Massif central, France). | C9: Rock glacier | D9: rock glacier | E9: Q884736 | F9: 13507719g | G9: glacier > ice cover > glacial landform > landform > geomorphological unit | H9: exact_label | I9: exact_label | J9: no | K9: 100 | L9: 50 | O9: YES | P9: YES | U9: MÃ©zenc | V9: =COUNTIF(C9:C199, U9) -> 1
A10: 1131185 | B10: Les Â« riviÃ¨res de pierres Â» : une formation en marge des catÃ©gories classiques. Questions posÃ©es dans le cas du massif du MÃ©zenc (Velay oriental, Sud-Est du Massif central, France). | C10: Rock glacier | D10: rock glacier | E10: Q884736 | F10: 13507719g | G10: glacier > ice cover > glacial landform > landform > geographical feature | H10: exact_label | I10: exact_label | J10: no | K10: 100 | L10: 50 | O10: YES | P10: YES | U10: Morphologie et processus pÃ©riglaciaires | V10: =COUNTIF(C10:C200, U10) -> 1
A11: 1131185 | B11: Les Â« riviÃ¨res de pierres Â» : une formation en marge des catÃ©gories classiques. Questions posÃ©es dans le cas du massif du MÃ©zenc (Velay oriental, Sud-Est du Massif central, France). | C11: Rock glacier | D11: rock glacier | E11: Q884736 | F11: 13507719g | G11: glacier > ice cover > glacial landform > landform > geographic location | H11: exact_label | I11: exact_label | J11: no | K11: 100 | L11: 50 | O11: YES | P11: YES | U11: RiviÃ¨re de pierres | V11: =COUNTIF(C11:C201, U11) -> 1 | W11: Total articles | X11: Total keywords | Y11: Correct Wikidata label | Z11: Incorrect Wikidata label | AA11: # QID in Wikidata | AB11: # BNF_Id | AC11: % Correct Wikidata label | AD11: % Incorrect Wikidata label | AE11: % # QID in Wikidata | AF11: % # BNF_Id
A12: 1131185 | B12: Les Â« riviÃ¨res de pierres Â» : une formation en marge des catÃ©gories classiques. Questions posÃ©es dans le cas du massif du MÃ©zenc (Velay oriental, Sud-Est du Massif central, France). | C12: Rock glacier | D12: rock glacier | E12: Q884736 | F12: 13507719g | G12: glacier > perennial ice or snowâ€covered land > landform > geomorphological unit > natural geographic object | H12: exact_label | I12: exact_label | J12: no | K12: 100 | L12: 50 | O12: YES | P12: YES | U12: Glacier rocheux | V12: =COUNTIF(C12:C202, U12) -> 29 | W12: {=COUNTA(_xlfn.UNIQUE(_xlfn._xlws.FILTER(B2:B192, B2:B192<>"")))} -> 9 | X12: {=COUNTA(_xlfn.UNIQUE(_xlfn._xlws.FILTER(C2:C192, C2:C192<>"")))} -> 48 | Y12: {=COUNTA(_xlfn.UNIQUE(_xlfn._xlws.FILTER(C2:C192 & E2:E192, O2:O192="YES")))} -> 41 | Z12: {=COUNTA(_xlfn.UNIQUE(_xlfn._xlws.FILTER(C2:C192 & E2:E192, O2:O192="NO")))} -> 7 | AA12: {=COUNTA(_xlfn.UNIQUE(_xlfn._xlws.FILTER(E2:E192, E2:E192<>"")))} -> 17 | AB12: {=COUNTA(_xlfn.UNIQUE(_xlfn._xlws.FILTER(F2:F192, F2:F192<>"")))} -> 2 | AC12: =Y12 / (Y12 + Z12) -> 0.85416667 | AD12: =Z12 / (Y12 + Z12) -> 0.14583333 | AE12: =AA12 / X12 -> 0.35416667 | AF12: =AB12 / X12 -> 0.041666667
A13: 1131185 | B13: Les Â« riviÃ¨res de pierres Â» : une formation en marge des catÃ©gories classiques. Questions posÃ©es dans le cas du massif du MÃ©zenc (Velay oriental, Sud-Est du Massif central, France). | C13: Rock glacier | D13: rock glacier | E13: Q884736 | F13: 13507719g | G13: glacier > perennial ice or snowâ€covered land > landform > geographical feature > geographic entity | H13: exact_label | I13: exact_label | J13: no | K13: 100 | L13: 50 | O13: YES | P13: YES | U13: Velay oriental | V13: =COUNTIF(C13:C203, U13) -> 1
A14: 1131185 | B14: Les Â« riviÃ¨res de pierres Â» : une formation en marge des catÃ©gories classiques. Questions posÃ©es dans le cas du massif du MÃ©zenc (Velay oriental, Sud-Est du Massif central, France). | C14: Rock glacier | D14: rock glacier | E14: Q884736 | F14: 13507719g | G14: glacier > perennial ice or snowâ€covered land > landform > geographical feature > concrete object | H14: exact_label | I14: exact_label | J14: no | K14: 100 | L14: 50 | O14: YES | P14: YES | U14: Massif central franÃ§ais | V14: =COUNTIF(C14:C204, U14) -> 1
A15: 1131185 | B15: Les Â« riviÃ¨res de pierres Â» : une formation en marge des catÃ©gories classiques. Questions posÃ©es dans le cas du massif du MÃ©zenc (Velay oriental, Sud-Est du Massif central, France). | C15: Rock glacier | D15: rock glacier | E15: Q884736 | F15: 13507719g | G15: glacier > perennial ice or snowâ€covered land > landform > geographical feature > physical location | H15: exact_label | I15: exact_label | J15: no | K15: 100 | L15: 50 | O15: YES | P15: YES | U15: Tardiglaciaire | V15: =COUNTIF(C15:C205, U15) -> 1
A16: 1131185 | B16: Les Â« riviÃ¨res de pierres Â» : une formation en marge des catÃ©gories classiques. Questions posÃ©es dans le cas du massif du MÃ©zenc (Velay oriental, Sud-Est du Massif central, France). | C16: Rock glacier | D16: rock glacier | E16: Q884736 | F16: 13507719g | G16: glacier > perennial ice or snowâ€covered land > landform > geographic location > geographic entity | H16: exact_label | I16: exact_label | J16: no | K16: 100 | L16: 50 | O16: YES | P16: YES | U16: Dunkl kernel | V16: =COUNTIF(C16:C206, U16) -> 1
A17: 1131185 | B17: Les Â« riviÃ¨res de pierres Â» : une formation en marge des catÃ©gories classiques. Questions posÃ©es dans le cas du massif du MÃ©zenc (Velay oriental, Sud-Est du Massif central, France). | C17: Rock glacier | D17: rock glacier | E17: Q884736 | F17: 13507719g | G17: glacier > perennial ice or snowâ€covered land > landform > geographic location > physical location | H17: exact_label | I17: exact_label | J17: no | K17: 100 | L17: 50 | O17: YES | P17: YES | U17: Dihedral root systems | V17: =COUNTIF(C17:C207, U17) -> 1
A18: 1131185 | B18: Les Â« riviÃ¨res de pierres Â» : une formation en marge des catÃ©gories classiques. Questions posÃ©es dans le cas du massif du MÃ©zenc (Velay oriental, Sud-Est du Massif central, France). | C18: Rock glacier | D18: rock glacier | E18: Q884736 | F18: 13507719g | G18: frozen ground > soil > granular material > material > substance | H18: exact_label | I18: exact_label | J18: no | K18: 100 | L18: 50 | O18: YES | P18: YES | U18: Generalized Bessel function | V18: =COUNTIF(C18:C208, U18) -> 1
A19: 1131185 | B19: Les Â« riviÃ¨res de pierres Â» : une formation en marge des catÃ©gories classiques. Questions posÃ©es dans le cas du massif du MÃ©zenc (Velay oriental, Sud-Est du Massif central, France). | C19: Rock glacier | D19: rock glacier | E19: Q884736 | F19: 13507719g | G19: frozen ground > soil > granular material > material > product | H19: exact_label | I19: exact_label | J19: no | K19: 100 | L19: 50 | O19: YES | P19: YES | U19: Structural dynamics | V19: =COUNTIF(C19:C209, U19) -> 8
A20: 1131185 | B20: Les Â« riviÃ¨res de pierres Â» : une formation en marge des catÃ©gories classiques. Questions posÃ©es dans le cas du massif du MÃ©zenc (Velay oriental, Sud-Est du Massif central, France). | C20: Rock glacier | D20: rock glacier | E20: Q884736 | F20: 13507719g | G20: frozen ground > soil > granular material > continuum > physical substance | H20: exact_label | I20: exact_label | J20: no | K20: 100 | L20: 50 | O20: YES | P20: YES | U20: Model identification | V20: =COUNTIF(C20:C210, U20) -> 1
A21: 1131185 | B21: Les Â« riviÃ¨res de pierres Â» : une formation en marge des catÃ©gories classiques. Questions posÃ©es dans le cas du massif du MÃ©zenc (Velay oriental, Sud-Est du Massif central, France). | C21: Rock glacier | D21: rock glacier | E21: Q884736 | F21: 13507719g | G21: frozen ground > soil > heterogeneous mixture > mixture > chemical substance | H21: exact_label | I21: exact_label | J21: no | K21: 100 | L21: 50 | O21: YES | P21: YES | U21: Computational stochastic dynamics | V21: =COUNTIF(C21:C211, U21) -> 1
A22: 1131185 | B22: Les Â« riviÃ¨res de pierres Â» : une formation en marge des catÃ©gories classiques. Questions posÃ©es dans le cas du massif du MÃ©zenc (Velay oriental, Sud-Est du Massif central, France). | C22: Rock glacier | D22: rock glacier | E22: Q884736 | F22: 13507719g | G22: frozen ground > soil > natural system > system > collective entity | H22: exact_label | I22: exact_label | J22: no | K22: 100 | L22: 50 | O22: YES | P22: YES | U22: Mode crossing | V22: =COUNTIF(C22:C212, U22) -> 1
A23: 1131185 | B23: Les Â« riviÃ¨res de pierres Â» : une formation en marge des catÃ©gories classiques. Questions posÃ©es dans le cas du massif du MÃ©zenc (Velay oriental, Sud-Est du Massif central, France). | C23: Rock glacier | D23: rock glacier | E23: Q884736 | F23: 13507719g | G23: frozen ground > soil > natural system > system > abstract entity | H23: exact_label | I23: exact_label | J23: no | K23: 100 | L23: 50 | O23: YES | P23: YES | U23: Experimental modal analysis | V23: =COUNTIF(C23:C213, U23) -> 1
A24: 1131185 | B24: Les Â« riviÃ¨res de pierres Â» : une formation en marge des catÃ©gories classiques. Questions posÃ©es dans le cas du massif du MÃ©zenc (Velay oriental, Sud-Est du Massif central, France). | C24: Rock glacier | D24: rock glacier | E24: Q884736 | F24: 13507719g | G24: frozen ground > soil > natural system > system > object | H24: exact_label | I24: exact_label | J24: no | K24: 100 | L24: 50 | O24: YES | P24: YES | U24: Uncertainty Quantification | V24: =COUNTIF(C24:C214, U24) -> 36
... A32: 1131185 | B32: Les Â« riviÃ¨res de pierres Â» : une formation en marge des catÃ©gories classiques. Questions posÃ©es dans le cas du massif du MÃ©zenc (Velay oriental, Sud-Est du Massif central, France). | C32: Rock glacier | D32: rock glacier | E32: Q884736 | F32: 13507719g | G32: frozen ground > soil > building material > construction product > product | H32: exact_label | I32: exact_label | J32: no | K32: 100 | L32: 50 | O32: YES | P32: YES | U32: Vibration | V32: =COUNTIF(C32:C222, U32) -> 1
A33: 1131185 | B33: Les Â« riviÃ¨res de pierres Â» : une formation en marge des catÃ©gories classiques. Questions posÃ©es dans le cas du massif du MÃ©zenc (Velay oriental, Sud-Est du Massif central, France). | C33: Periglacial morphology and process | H33: none | I33: none | J33: no | K33: 0 | L33: 0 | O33: YES | P33: YES | U33: Computational Vibroacoustics | V33: =COUNTIF(C33:C223, U33) -> 1
A34: 1131185 | B34: Les Â« riviÃ¨res de pierres Â» : une formation en marge des catÃ©gories classiques. Questions posÃ©es dans le cas du massif du MÃ©zenc (Velay oriental, Sud-Est du Massif central, France). | C34: Pleistocene | D34: Pleistocene | E34: Q25546 | F34: 11945805t | H34: context | I34: context | J34: no | K34: 100 | L34: 110 | M34: Q312468;Q754897 | N34: epoch;series | O34: YES | P34: YES | U34: Nonlinear structural dynamics | V34: =COUNTIF(C34:C224, U34) -> 1
A35: 1131185 | B35: Les Â« riviÃ¨res de pierres Â» : une formation en marge des catÃ©gories classiques. Questions posÃ©es dans le cas du massif du MÃ©zenc (Velay oriental, Sud-Est du Massif central, France). | C35: Late Glacial | D35: Late Glacial Maximum | E35: Q2741484 | H35: context | I35: context | J35: no | K35: 75 | L35: 45 | M35: Q602963 | N35: glacial period | O35: YES | P35: YES | U35: Mistuned bladed disk | V35: =COUNTIF(C35:C225, U35) -> 1
A36: 1131185 | B36: Les Â« riviÃ¨res de pierres Â» : une formation en marge des catÃ©gories classiques. Questions posÃ©es dans le cas du massif du MÃ©zenc (Velay oriental, Sud-Est du Massif central, France). | C36: Eastern Velay | H36: none | I36: none | J36: no | K36: 0 | L36: 0 | O36: YES | P36: YES | U36: Geometrical nonlinearities | V36: =COUNTIF(C36:C226, U36) -> 1
A37: 1131185 | B37: Les Â« riviÃ¨res de pierres Â» : une formation en marge des catÃ©gories classiques. Questions posÃ©es dans le cas du massif du MÃ©zenc (Velay oriental, Sud-Est du Massif central, France). | C37: MÃ©zenc | D37: Mezenc | E37: Q128548547 | H37: context | I37: context | J37: no | K37: 100 | L37: 112 | M37: Q15069452 | N37: Natura 2000 site | O37: NO | P37: NO | Q37: keyword contains special character. The QID identified has no label defined. Potential QIDs: massif du Mézenc (Q3297689), Mont Mézenc Sud (Q34878583), Mount Mézenc (Q1267547), and Mont Mézenc Nord (Q34878573)… BnF IDs: massif du Mézenc (cb40616660p), Mont Mézenc and Nord(cb15199595z) | U37: Multiscale methods | V37: =COUNTIF(C37:C227, U37) -> 1
A38: 1131185 | B38: Les Â« riviÃ¨res de pierres Â» : une formation en marge des catÃ©gories classiques. Questions posÃ©es dans le cas du massif du MÃ©zenc (Velay oriental, Sud-Est du Massif central, France). | C38: Morphologie et processus pÃ©riglaciaires | H38: none | I38: none | J38: no | K38: 0 | L38: 0 | O38: YES | P38: YES | Q38: Contains special character | U38: Neural Networks | V38: =COUNTIF(C38:C228, U38) -> 6
A39: 1131185 | B39: Les Â« riviÃ¨res de pierres Â» : une formation en marge des catÃ©gories classiques. Questions posÃ©es dans le cas du massif du MÃ©zenc (Velay oriental, Sud-Est du Massif central, France). | C39: RiviÃ¨re de pierres | D39: RiviÃ¨re de pierre | E39: Q113579337 | H39: context | I39: context | J39: no | K39: 97.1 | L39: 109.3 | M39: Q55488 | N39: railway station | O39: NO | P39: NO | Q39: mismatched on the context | U39: High-dimensional approximation | V39: =COUNTIF(C39:C229, U39) -> 1
A40: 1131185 | B40: Les Â« riviÃ¨res de pierres Â» : une formation en marge des catÃ©gories classiques. Questions posÃ©es dans le cas du massif du MÃ©zenc (Velay oriental, Sud-Est du Massif central, France). | C40: Glacier rocheux | D40: rock glacier | E40: Q884736 | F40: 13507719g | G40: glacier > ice cover > body of water > region > geographical feature | H40: exact_label | I40: exact_label | J40: no | K40: 100 | L40: 50 | O40: YES | Q40: same as row 4 to 32 | U40: Computational homogenization | V40: =COUNTIF(C40:C230, U40) -> 1
A41: 1131185 | B41: Les Â« riviÃ¨res de pierres Â» : une formation en marge des catÃ©gories classiques. Questions posÃ©es dans le cas du massif du MÃ©zenc (Velay oriental, Sud-Est du Massif central, France). | C41: Glacier rocheux | D41: rock glacier | E41: Q884736 | F41: 13507719g | G41: glacier > ice cover > body of water > physico-geographical object > geographical feature | H41: exact_label | I41: exact_label | J41: no | K41: 100 | L41: 50 | O41: YES | Q41: same as row 4 to 32 | U41: Nonlinear homogenization | V41: =COUNTIF(C41:C231, U41) -> 1
A42: 1131185 | B42: Les Â« riviÃ¨res de pierres Â» : une formation en marge des catÃ©gories classiques. Questions posÃ©es dans le cas du massif du MÃ©zenc (Velay oriental, Sud-Est du Massif central, France). | C42: Glacier rocheux | D42: rock glacier | E42: Q884736 | F42: 13507719g | G42: glacier > ice cover > body of water > physico-geographical object > physical object | H42: exact_label | I42: exact_label | J42: no | K42: 100 | L42: 50 | O42: YES | Q42: same as row 4 to 32 | U42: Drillstring dynamics | V42: =COUNTIF(C42:C232, U42) -> 1
A43: 1131185 | B43: Les Â« riviÃ¨res de pierres Â» : une formation en marge des catÃ©gories classiques. Questions posÃ©es dans le cas du massif du MÃ©zenc (Velay oriental, Sud-Est du Massif central, France). | C43: Glacier rocheux | D43: rock glacier | E43: Q884736 | F43: 13507719g | G43: glacier > ice cover > body of water > habitat > region | H43: exact_label | I43: exact_label | J43: no | K43: 100 | L43: 50 | O43: YES | Q43: same as row 4 to 32 | U43: Horizontal drillstring | V43: =COUNTIF(C43:C233, U43) -> 1
A44: 1131185 | B44: Les Â« riviÃ¨res de pierres Â» : une formation en marge des catÃ©gories classiques. Questions posÃ©es dans le cas du massif du MÃ©zenc (Velay oriental, Sud-Est du Massif central, France). | C44: Glacier rocheux | D44: rock glacier | E44: Q884736 | F44: 13507719g | G44: glacier > ice cover > body of water > habitat > natural environment | H44: exact_label | I44: exact_label | J44: no | K44: 100 | L44: 50 | O44: YES | Q44: same as row 4 to 32; translated in French? | U44: Parametric probabilistic approach | V44: =COUNTIF(C44:C234, U44) -> 1
A45: 1131185 | B45: Les Â« riviÃ¨res de pierres Â» : une formation en marge des catÃ©gories classiques. Questions posÃ©es dans le cas du massif du MÃ©zenc (Velay oriental, Sud-Est du Massif central, France). | C45: Glacier rocheux | D45: rock glacier | E45: Q884736 | F45: 13507719g | G45: glacier > ice cover > glacial landform > landform > geomorphological unit | H45: exact_label | I45: exact_label | J45: no | K45: 100 | L45: 50 | O45: YES | Q45: same as row 4 to 32; translated in French? | U45: Robust optimization | V45: =COUNTIF(C45:C235, U45) -> 6
A46: 1131185 | B46: Les Â« riviÃ¨res de pierres Â» : une formation en marge des catÃ©gories classiques. Questions posÃ©es dans le cas du massif du MÃ©zenc (Velay oriental, Sud-Est du Massif central, France). | C46: Glacier rocheux | D46: rock glacier | E46: Q884736 | F46: 13507719g | G46: glacier > ice cover > glacial landform > landform > geographical feature | H46: exact_label | I46: exact_label | J46: no | K46: 100 | L46: 50 | O46: YES | Q46: same as row 4 to 32; translated in French? | U46: Optimal sensor placement | V46: =COUNTIF(C46:C236, U46) -> 1
A47: 1131185 | B47: Les Â« riviÃ¨res de pierres Â» : une formation en marge des catÃ©gories classiques. Questions posÃ©es dans le cas du massif du MÃ©zenc (Velay oriental, Sud-Est du Massif central, France). | C47: Glacier rocheux | D47: rock glacier | E47: Q884736 | F47: 13507719g | G47: glacier > ice cover > glacial landform > landform > geographic location | H47: exact_label | I47: exact_label | J47: no | K47: 100 | L47: 50 | O47: YES | Q47: same as row 4 to 32; translated in French? | U47: Model updating | V47: =COUNTIF(C47:C237, U47) -> 1
A48: 1131185 | B48: Les Â« riviÃ¨res de pierres Â» : une formation en marge des catÃ©gories classiques. Questions posÃ©es dans le cas du massif du MÃ©zenc (Velay oriental, Sud-Est du Massif central, France). | C48: Glacier rocheux | D48: rock glacier | E48: Q884736 | F48: 13507719g | G48: glacier > perennial ice or snowâ€covered land > landform > geomorphological unit > natural geographic object | H48: exact_label | I48: exact_label | J48: no | K48: 100 | L48: 50 | O48: YES | Q48: same as row 4 to 32; translated in French? | U48: Bayesian inference | V48: =COUNTIF(C48:C238, U48) -> 8
A49: 1131185 | B49: Les Â« riviÃ¨res de pierres Â» : une formation en marge des catÃ©gories classiques. Questions posÃ©es dans le cas du massif du MÃ©zenc (Velay oriental, Sud-Est du Massif central, France). | C49: Glacier rocheux | D49: rock glacier | E49: Q884736 | F49: 13507719g | G49: glacier > perennial ice or snowâ€covered land > landform > geographical feature > geographic entity | H49: exact_label | I49: exact_label | J49: no | K49: 100 | L49: 50 | O49: YES | Q49: same as row 4 to 32; translated in French? | U49: Uncertain position | V49: =COUNTIF(C49:C239, U49) -> 1
A50: 1131185 | B50: Les Â« riviÃ¨res de pierres Â» : une formation en marge des catÃ©gories classiques. Questions posÃ©es dans le cas du massif du MÃ©zenc (Velay oriental, Sud-Est du Massif central, France). | C50: Glacier rocheux | D50: rock glacier | E50: Q884736 | F50: 13507719g | G50: glacier > perennial ice or snowâ€covered land > landform > geographical feature > concrete object | H50: exact_label | I50: exact_label | J50: no | K50: 100 | L50: 50 | O50: YES | Q50: same as row 4 to 32; translated in French?
A51: 1131185 | B51: Les Â« riviÃ¨res de pierres Â» : une formation en marge des catÃ©gories classiques. Questions posÃ©es dans le cas du massif du MÃ©zenc (Velay oriental, Sud-Est du Massif central, France). | C51: Glacier rocheux | D51: rock glacier | E51: Q884736 | F51: 13507719g | G51: glacier > perennial ice or snowâ€covered land > landform > geographical feature > physical location | H51: exact_label | I51: exact_label | J51: no | K51: 100 | L51: 50 | O51: YES | Q51: same as row 4 to 32; translated in French?
A52: 1131185 | B52: Les Â« riviÃ¨res de pierres Â» : une formation en marge des catÃ©gories classiques. Questions posÃ©es dans le cas du massif du MÃ©zenc (Velay oriental, Sud-Est du Massif central, France). | C52: Glacier rocheux | D52: rock glacier | E52: Q884736 | F52: 13507719g | G52: glacier > perennial ice or snowâ€covered land > landform > geographic location > geographic entity | H52: exact_label | I52: exact_label | J52: no | K52: 100 | L52: 50 | O52: YES | Q52: same as row 4 to 32; translated in French?
A53: 1131185 | B53: Les Â« riviÃ¨res de pierres Â» : une formation en marge des catÃ©gories classiques. Questions posÃ©es dans le cas du massif du MÃ©zenc (Velay oriental, Sud-Est du Massif central, France). | C53: Glacier rocheux | D53: rock glacier | E53: Q884736 | F53: 13507719g | G53: glacier > perennial ice or snowâ€covered land > landform > geographic location > physical location | H53: exact_label | I53: exact_label | J53: no | K53: 100 | L53: 50 | O53: YES | Q53: same as row 4 to 32; translated in French?
A54: 1131185 | B54: Les Â« riviÃ¨res de pierres Â» : une formation en marge des catÃ©gories classiques. Questions posÃ©es dans le cas du massif du MÃ©zenc (Velay oriental, Sud-Est du Massif central, France). | C54: Glacier rocheux | D54: rock glacier | E54: Q884736 | F54: 13507719g | G54: frozen ground > soil > granular material > material > substance | H54: exact_label | I54: exact_label | J54: no | K54: 100 | L54: 50 | O54: YES | Q54: same as row 4 to 32; translated in French?
A55: 1131185 | B55: Les Â« riviÃ¨res de pierres Â» : une formation en marge des catÃ©gories classiques. Questions posÃ©es dans le cas du massif du MÃ©zenc (Velay oriental, Sud-Est du Massif central, France). | C55: Glacier rocheux | D55: rock glacier | E55: Q884736 | F55: 13507719g | G55: frozen ground > soil > granular material > material > product | H55: exact_label | I55: exact_label | J55: no | K55: 100 | L55: 50 | O55: YES | Q55: same as row 4 to 32; translated in French?
A56: 1131185 | B56: Les Â« riviÃ¨res de pierres Â» : une formation en marge des catÃ©gories classiques. Questions posÃ©es dans le cas du massif du MÃ©zenc (Velay oriental, Sud-Est du Massif central, France). | C56: Glacier rocheux | D56: rock glacier | E56: Q884736 | F56: 13507719g | G56: frozen ground > soil > granular material > continuum > physical substance | H56: exact_label | I56: exact_label | J56: no | K56: 100 | L56: 50 | O56: YES | Q56: same as row 4 to 32; translated in French?
A57: 1131185 | B57: Les Â« riviÃ¨res de pierres Â» : une formation en marge des catÃ©gories classiques. Questions posÃ©es dans le cas du massif du MÃ©zenc (Velay oriental, Sud-Est du Massif central, France). | C57: Glacier rocheux | D57: rock glacier | E57: Q884736 | F57: 13507719g | G57: frozen ground > soil > heterogeneous mixture > mixture > chemical substance | H57: exact_label | I57: exact_label | J57: no | K57: 100 | L57: 50 | O57: YES | Q57: same as row 4 to 32; translated in French?
A58: 1131185 | B58: Les Â« riviÃ¨res de pierres Â» : une formation en marge des catÃ©gories classiques. Questions posÃ©es dans le cas du massif du MÃ©zenc (Velay oriental, Sud-Est du Massif central, France). | C58: Glacier rocheux | D58: rock glacier | E58: Q884736 | F58: 13507719g | G58: frozen ground > soil > natural system > system > collective entity | H58: exact_label | I58: exact_label | J58: no | K58: 100 | L58: 50 | O58: YES | Q58: same as row 4 to 32; translated in French?
A59: 1131185 | B59: Les Â« riviÃ¨res de pierres Â» : une formation en marge des catÃ©gories classiques. Questions posÃ©es dans le cas du massif du MÃ©zenc (Velay oriental, Sud-Est du Massif central, France). | C59: Glacier rocheux | D59: rock glacier | E59: Q884736 | F59: 13507719g | G59: frozen ground > soil > natural system > system > abstract entity | H59: exact_label | I59: exact_label | J59: no | K59: 100 | L59: 50 | O59: YES | Q59: same as row 4 to 32; translated in French?
A60: 1131185 | B60: Les Â« riviÃ¨res de pierres Â» : une formation en marge des catÃ©gories classiques. Questions posÃ©es dans le cas du massif du MÃ©zenc (Velay oriental, Sud-Est du Massif central, France). | C60: Glacier rocheux | D60: rock glacier | E60: Q884736 | F60: 13507719g | G60: frozen ground > soil > natural system > system > object | H60: exact_label | I60: exact_label | J60: no | K60: 100 | L60: 50 | O60: YES | Q60: same as row 4 to 32; translated in French?
A61: 1131185 | B61: Les Â« riviÃ¨res de pierres Â» : une formation en marge des catÃ©gories classiques. Questions posÃ©es dans le cas du massif du MÃ©zenc (Velay oriental, Sud-Est du Massif central, France). | C61: Glacier rocheux | D61: rock glacier | E61: Q884736 | F61: 13507719g | G61: frozen ground > soil > natural system > natural object > object | H61: exact_label | I61: exact_label | J61: no | K61: 100 | L61: 50 | O61: YES | Q61: same as row 4 to 32; translated in French?
... A68: 1131185 | B68: Les Â« riviÃ¨res de pierres Â» : une formation en marge des catÃ©gories classiques. Questions posÃ©es dans le cas du massif du MÃ©zenc (Velay oriental, Sud-Est du Massif central, France). | C68: Glacier rocheux | D68: rock glacier | E68: Q884736 | F68: 13507719g | G68: frozen ground > soil > building material > construction product > product | H68: exact_label | I68: exact_label | J68: no | K68: 100 | L68: 50 | O68: YES | Q68: same as row 4 to 32; translated in French?
A69: 1131185 | B69: Les Â« riviÃ¨res de pierres Â» : une formation en marge des catÃ©gories classiques. Questions posÃ©es dans le cas du massif du MÃ©zenc (Velay oriental, Sud-Est du Massif central, France). | C69: Velay oriental | H69: none | I69: none | J69: no | K69: 0 | L69: 0 | O69: YES | Q69: same as row 36; translated in French?
A70: 1131185 | B70: Les Â« riviÃ¨res de pierres Â» : une formation en marge des catÃ©gories classiques. Questions posÃ©es dans le cas du massif du MÃ©zenc (Velay oriental, Sud-Est du Massif central, France). | C70: Massif central franÃ§ais | H70: none | I70: none | J70: no | K70: 0 | L70: 0 | O70: YES | Q70: same as row 37; translated in French?
A71: 1131185 | B71: Les Â« riviÃ¨res de pierres Â» : une formation en marge des catÃ©gories classiques. Questions posÃ©es dans le cas du massif du MÃ©zenc (Velay oriental, Sud-Est du Massif central, France). | C71: Tardiglaciaire | D71: Late Glacial Maximum | E71: Q2741484 | H71: exact_label | I71: exact_label | J71: no | K71: 100 | L71: 50 | M71: Q602963 | N71: glacial period | O71: YES | Q71: same as row 35; translated in French?
A72: 1148833 | B72: Dunkl kernel associated with dihedral group | C72: Dunkl kernel | H72: none | I72: none | J72: no | K72: 0 | L72: 0 | O72: YES | P72: YES | R72: =COUNTIF(O72:O74,"*YES*")/COUNTA(O72:O74) -> 1 | S72: =COUNTIF(P72:P74,"*YES*")/COUNTA(P72:P74) -> 1
A73: 1148833 | B73: Dunkl kernel associated with dihedral group | C73: Dihedral root systems | H73: none | I73: none | J73: no | K73: 0 | L73: 0 | O73: YES | P73: YES
A74: 1148833 | B74: Dunkl kernel associated with dihedral group | C74: Generalized Bessel function | H74: none | I74: none | J74: no | K74: 0 | L74: 0 | O74: YES | P74: YES
A75: 1158275 | B75: Experimental identification of a stochastic computational dynamical model using modal data measured for a family of built-up structures | C75: Structural dynamics | D75: structural dynamics | E75: Q811197 | G75: structural analysis > analysis > inquiry > seeking > activity | H75: exact_label | I75: exact_label | J75: no | K75: 100 | L75: 80 | M75: Q11862829 | N75: academic discipline | O75: YES | P75: YES | R75: =COUNTIF(O75:O129,"*YES*")/COUNTA(O75:O129) -> 0.94545455 | S75: =COUNTIF(P75:P129,"*YES*")/COUNTA(P75:P129) -> 1
A76: 1158275 | B76: Experimental identification of a stochastic computational dynamical model using modal data measured for a family of built-up structures | C76: Structural dynamics | D76: structural dynamics | E76: Q811197 | G76: structural analysis > analysis > inquiry > planned process > process | H76: exact_label | I76: exact_label | J76: no | K76: 100 | L76: 80 | M76: Q11862829 | N76: academic discipline | O76: YES | P76: YES
A77: 1158275 | B77: Experimental identification of a stochastic computational dynamical model using modal data measured for a family of built-up structures | C77: Structural dynamics | D77: structural dynamics | E77: Q811197 | G77: structural analysis > analysis > inquiry > planned process > intentional human activity | H77: exact_label | I77: exact_label | J77: no | K77: 100 | L77: 80 | M77: Q11862829 | N77: academic discipline | O77: YES | P77: YES
A78: 1158275 | B78: Experimental identification of a stochastic computational dynamical model using modal data measured for a family of built-up structures | C78: Structural dynamics | D78: structural dynamics | E78: Q811197 | G78: structural analysis > analysis > scholarly method > method > means | H78: exact_label | I78: exact_label | J78: no | K78: 100 | L78: 80 | M78: Q11862829 | N78: academic discipline | O78: YES | P78: YES
A79: 1158275 | B79: Experimental identification of a stochastic computational dynamical model using modal data measured for a family of built-up structures | C79: Model identification | H79: none | I79: none | J79: no | K79: 0 | L79: 0 | O79: YES | P79: YES
A80: 1158275 | B80: Experimental identification of a stochastic computational dynamical model using modal data measured for a family of built-up structures | C80: Computational stochastic dynamics | H80: none | I80: none | J80: no | K80: 0 | L80: 0 | O80: YES | P80: YES
A81: 1158275 | B81: Experimental identification of a stochastic computational dynamical model using modal data measured for a family of built-up structures | C81: Mode crossing | H81: none | I81: none | J81: no | K81: 0 | L81: 0 | O81: YES | P81: YES
A82: 1158275 | B82: Experimental identification of a stochastic computational dynamical model using modal data measured for a family of built-up structures | C82: Experimental modal analysis | H82: none | I82: none | J82: no | K82: 0 | L82: 0 | O82: YES | P82: YES
A83: 1158275 | B83: Experimental identification of a stochastic computational dynamical model using modal data measured for a family of built-up structures | C83: Uncertainty Quantification | D83: uncertainty quantification | E83: Q7882499 | G83: uncertainty analysis > analysis > inquiry > seeking > activity | H83: context | I83: context | J83: no | K83: 92.3 | L83: 110.4 | O83: YES | P83: YES
A84: 1158275 | B84: Experimental identification of a stochastic computational dynamical model using modal data measured for a family of built-up structures | C84: Uncertainty Quantification | D84: uncertainty quantification | E84: Q7882499 | G84: uncertainty analysis > analysis > inquiry > planned process > process | H84: context | I84: context | J84: no | K84: 92.3 | L84: 110.4 | O84: YES | P84: YES
A85: 1158275 | B85: Experimental identification of a stochastic computational dynamical model using modal data measured for a family of built-up structures | C85: Uncertainty Quantification | D85: uncertainty quantification | E85: Q7882499 | G85: uncertainty analysis > analysis > inquiry > planned process > intentional human activity | H85: context | I85: context | J85: no | K85: 92.3 | L85: 110.4 | O85: YES | P85: YES
A86: 1158275 | B86: Experimental identification of a stochastic computational dynamical model using modal data measured for a family of built-up structures | C86: Uncertainty Quantification | D86: uncertainty quantification | E86: Q7882499 | G86: uncertainty analysis > analysis > scholarly method > method > means | H86: context | I86: context | J86: no | K86: 92.3 | L86: 110.4 | O86: YES | P86: YES
A87: 1158275 | B87: Experimental identification of a stochastic computational dynamical model using modal data measured for a family of built-up structures | C87: Uncertainty Quantification | D87: uncertainty quantification | E87: Q7882499 | G87: uncertainty analysis > risk analysis > decision analysis > analysis > inquiry | H87: context | I87: context | J87: no | K87: 92.3 | L87: 110.4 | O87: YES | P87: YES
A88: 1158275 | B88: Experimental identification of a stochastic computational dynamical model using modal data measured for a family of built-up structures | C88: Uncertainty Quantification | D88: uncertainty quantification | E88: Q7882499 | G88: uncertainty analysis > risk analysis > decision analysis > analysis > scholarly method | H88: context | I88: context | J88: no | K88: 92.3 | L88: 110.4 | O88: YES | P88: YES
A89: 1158275 | B89: Experimental identification of a stochastic computational dynamical model using modal data measured for a family of built-up structures | C89: Uncertainty Quantification | D89: uncertainty quantification | E89: Q7882499 | G89: uncertainty analysis > risk analysis > analysis > inquiry > seeking | H89: context | I89: context | J89: no | K89: 92.3 | L89: 110.4 | O89: YES | P89: YES
A90: 1158275 | B90: Experimental identification of a stochastic computational dynamical model using modal data measured for a family of built-up structures | C90: Uncertainty Quantification | D90: uncertainty quantification | E90: Q7882499 | G90: uncertainty analysis > risk analysis > analysis > inquiry > planned process | H90: context | I90: context | J90: no | K90: 92.3 | L90: 110.4 | O90: YES | P90: YES
A91: 1158275 | B91: Experimental identification of a stochastic computational dynamical model using modal data measured for a family of built-up structures | C91: Uncertainty Quantification | D91: uncertainty quantification | E91: Q7882499 | G91: uncertainty analysis > risk analysis > analysis > scholarly method > method | H91: context | I91: context | J91: no | K91: 92.3 | L91: 110.4 | O91: YES | P91: YES
A92: 1158278 | B92: Global reduced-order model adapted to the low- and medium-frequency analysis of complex dynamical structures | C92: Structural dynamics | D92: structural dynamics | E92: Q811197 | G92: structural analysis > analysis > inquiry > seeking > activity | H92: exact_label | I92: exact_label | J92: no | K92: 100 | L92: 80 | M92: Q11862829 | N92: academic discipline | O92: YES | P92: YES
A93: 1158278 | B93: Global reduced-order model adapted to the low- and medium-frequency analysis of complex dynamical structures | C93: Structural dynamics | D93: structural dynamics | E93: Q811197 | G93: structural analysis > analysis > inquiry > planned process > process | H93: exact_label | I93: exact_label | J93: no | K93: 100 | L93: 80 | M93: Q11862829 | N93: academic discipline | O93: YES | P93: YES
A94: 1158278 | B94: Global reduced-order model adapted to the low- and medium-frequency analysis of complex dynamical structures | C94: Structural dynamics | D94: structural dynamics | E94: Q811197 | G94: structural analysis > analysis > inquiry > planned process > intentional human activity | H94: exact_label | I94: exact_label | J94: no | K94: 100 | L94: 80 | M94: Q11862829 | N94: academic discipline | O94: YES | P94: YES
A95: 1158278 | B95: Global reduced-order model adapted to the low- and medium-frequency analysis of complex dynamical structures | C95: Structural dynamics | D95: structural dynamics | E95: Q811197 | G95: structural analysis > analysis > scholarly method > method > means | H95: exact_label | I95: exact_label | J95: no | K95: 100 | L95: 80 | M95: Q11862829 | N95: academic discipline | O95: YES | P95: YES
A96: 1158278 | B96: Global reduced-order model adapted to the low- and medium-frequency analysis of complex dynamical structures | C96: Reduced-order model | H96: none | I96: none | J96: no | K96: 0 | L96: 0 | O96: YES | P96: YES
A97: 1158278 | B97: Global reduced-order model adapted to the low- and medium-frequency analysis of complex dynamical structures | C97: Global modes | D97: Global mode | E97: Q25325283 | H97: context | I97: context | J97: no | K97: 95.7 | L97: 108.4 | O97: NO | P97: YES | Q97: disambiguation page (no description defined)
A98: 1158278 | B98: Global reduced-order model adapted to the low- and medium-frequency analysis of complex dynamical structures | C98: Computational model | D98: computational model | E98: Q1122506 | G98: mathematical model > mathematical object > abstract entity > entity | H98: context | I98: context | J98: no | K98: 94.7 | L98: 110.8 | O98: YES | P98: YES
A99: 1158278 | B99: Global reduced-order model adapted to the low- and medium-frequency analysis of complex dynamical structures | C99: Computational model | D99: computational model | E99: Q1122506 | G99: mathematical model > conceptual model > knowledge organization system > conceptual system > system | H99: context | I99: context | J99: no | K99: 94.7 | L99: 110.8 | O99: YES | P99: YES
A100: 1158278 | B100: Global reduced-order model adapted to the low- and medium-frequency analysis of complex dynamical structures | C100: Computational model | D100: computational model | E100: Q1122506 | G100: mathematical model > conceptual model > knowledge organization system > conceptual system > artificial object | H100: context | I100: context | J100: no | K100: 94.7 | L100: 110.8 | O100: YES | P100: YES
A101: 1158278 | B101: Global reduced-order model adapted to the low- and medium-frequency analysis of complex dynamical structures | C101: Computational model | D101: computational model | E101: Q1122506 | G101: mathematical model > conceptual model > knowledge organization system > conceptual system > abstract entity | H101: context | I101: context | J101: no | K101: 94.7 | L101: 110.8 | O101: YES | P101: YES
A102: 1158278 | B102: Global reduced-order model adapted to the low- and medium-frequency analysis of complex dynamical structures | C102: Computational model | D102: computational model | E102: Q1122506 | G102: mathematical model > conceptual model > knowledge organization system > conceptual system > concept | H102: context | I102: context | J102: no | K102: 94.7 | L102: 110.8 | O102: YES | P102: YES
A103: 1158278 | B103: Global reduced-order model adapted to the low- and medium-frequency analysis of complex dynamical structures | C103: Computational model | D103: computational model | E103: Q1122506 | G103: mathematical model > conceptual model > knowledge organization system > model > artificial object | H103: context | I103: context | J103: no | K103: 94.7 | L103: 110.8 | O103: YES | P103: YES
A104: 1158278 | B104: Global reduced-order model adapted to the low- and medium-frequency analysis of complex dynamical structures | C104: Computational model | D104: computational model | E104: Q1122506 | G104: mathematical model > conceptual model > knowledge organization system > model > information | H104: context | I104: context | J104: no | K104: 94.7 | L104: 110.8 | O104: YES | P104: YES
A105: 1158278 | B105: Global reduced-order model adapted to the low- and medium-frequency analysis of complex dynamical structures | C105: Computational model | D105: computational model | E105: Q1122506 | G105: mathematical model > conceptual model > knowledge organization system > reference work > tertiary source | H105: context | I105: context | J105: no | K105: 94.7 | L105: 110.8 | O105: YES | P105: YES
A106: 1158278 | B106: Global reduced-order model adapted to the low- and medium-frequency analysis of complex dynamical structures | C106: Computational model | D106: computational model | E106: Q1122506 | G106: mathematical model > conceptual model > knowledge organization system > reference work > learning material | H106: context | I106: context | J106: no | K106: 94.7 | L106: 110.8 | O106: YES | P106: YES
A107: 1158278 | B107: Global reduced-order model adapted to the low- and medium-frequency analysis of complex dynamical structures | C107: Computational model | D107: computational model | E107: Q1122506 | G107: mathematical model > conceptual model > knowledge organization system > reference work > creative work | H107: context | I107: context | J107: no | K107: 94.7 | L107: 110.8 | O107: YES | P107: YES
A108: 1158278 | B108: Global reduced-order model adapted to the low- and medium-frequency analysis of complex dynamical structures | C108: Computational model | D108: computational model | E108: Q1122506 | G108: mathematical model > conceptual model > knowledge organization system > reference work > document | H108: context | I108: context | J108: no | K108: 94.7 | L108: 110.8 | O108: YES | P108: YES
A109: 1158278 | B109: Global reduced-order model adapted to the low- and medium-frequency analysis of complex dynamical structures | C109: Computational model | D109: computational model | E109: Q1122506 | G109: mathematical model > conceptual model > knowledge organization system > reference work > written work | H109: context | I109: context | J109: no | K109: 94.7 | L109: 110.8 | O109: YES | P109: YES
... A126: 1158278 | B126: Global reduced-order model adapted to the low- and medium-frequency analysis of complex dynamical structures | C126: Computational model | D126: computational model | E126: Q1122506 | G126: mathematical model > mathematical object > scientific object > object > entity | H126: context | I126: context | J126: no | K126: 94.7 | L126: 110.8 | O126: YES | P126: YES
A127: 1158278 | B127: Global reduced-order model adapted to the low- and medium-frequency analysis of complex dynamical structures | C127: Frequency range | D127: frequency range | E127: Q2800657 | G127: range > part > entity | H127: context | I127: context | J127: no | K127: 93.3 | L127: 107 | O127: NO | P127: YES | Q127: disambiguation page (no description defined)
A128: 1158278 | B128: Global reduced-order model adapted to the low- and medium-frequency analysis of complex dynamical structures | C128: Frequency range | D128: frequency range | E128: Q2800657 | G128: range > part > entity | H128: context | I128: context | J128: no | K128: 93.3 | L128: 107 | O128: NO | P128: YES | Q128: disambiguation page (no description defined)
A129: 1158278 | B129: Global reduced-order model adapted to the low- and medium-frequency analysis of complex dynamical structures | C129: Medium-frequency range | H129: none | I129: none | J129: no | K129: 0 | L129: 0 | O129: YES | P129: YES
...

Sheet Sheet1
A1: {=_xlfn.UNIQUE(Wikidata_upec_chemical_20!A:A)} -> docid | B1: {=_xlfn.UNIQUE(Wikidata_upec_chemical_20!C:C)} -> keyword | D1: QID | E1: BNF_id | G1: Total articles | H1: =COUNTA($A$2:$A$21) -> 20
A2: 1006198 | B2: Mixed convection | C2: =VLOOKUP(B2,Wikidata_upec_chemical_20!$C:$O,13,FALSE) -> ok | D2: =IF(VLOOKUP(B2,Wikidata_upec_chemical_20!$C:$O,3,FALSE)<>0,"yes","no") -> no | E2: =IF(VLOOKUP(B2,Wikidata_upec_chemical_20!$C:$O,4,FALSE)<>0,"yes","no") -> no | G2: Total | H2: =COUNTA($B$2:$B$96) -> 95
A3: 1025697 | B3: Poiseuille-Rayleigh-BÃ©nard flow | C3: =VLOOKUP(B3,Wikidata_upec_chemical_20!$C:$O,13,FALSE) -> ok | D3: =IF(VLOOKUP(B3,Wikidata_upec_chemical_20!$C:$O,3,FALSE)<>0,"yes","no") -> no | E3: =IF(VLOOKUP(B3,Wikidata_upec_chemical_20!$C:$O,4,FALSE)<>0,"yes","no") -> no | G3: ok | H3: =COUNTIF($C$2:$C$96,G3) -> 73 | I3: =H3/H2 -> 0.76842105
A4: 1060481 | B4: Convective instability | C4: =VLOOKUP(B4,Wikidata_upec_chemical_20!$C:$O,13,FALSE) -> ok | D4: =IF(VLOOKUP(B4,Wikidata_upec_chemical_20!$C:$O,3,FALSE)<>0,"yes","no") -> yes | E4: =IF(VLOOKUP(B4,Wikidata_upec_chemical_20!$C:$O,4,FALSE)<>0,"yes","no") -> no | G4: Wrong | H4: =COUNTIF($C$2:$C$96,G4) -> 22 | I4: =1-I3 -> 0.23157895
A5: 1064801 | B5: Rectangular channel | C5: =VLOOKUP(B5,Wikidata_upec_chemical_20!$C:$O,13,FALSE) -> ok | D5: =IF(VLOOKUP(B5,Wikidata_upec_chemical_20!$C:$O,3,FALSE)<>0,"yes","no") -> no | E5: =IF(VLOOKUP(B5,Wikidata_upec_chemical_20!$C:$O,4,FALSE)<>0,"yes","no") -> no | G5: QID | H5: =COUNTIF($D$2:$D$96,"yes") -> 44 | I5: =H5/H2 -> 0.46315789
A6: 1067996 | B6: Harmonic inlet excitation | C6: =VLOOKUP(B6,Wikidata_upec_chemical_20!$C:$O,13,FALSE) -> ok | D6: =IF(VLOOKUP(B6,Wikidata_upec_chemical_20!$C:$O,3,FALSE)<>0,"yes","no") -> no | E6: =IF(VLOOKUP(B6,Wikidata_upec_chemical_20!$C:$O,4,FALSE)<>0,"yes","no") -> no | G6: BNF_ID | H6: =COUNTIF($E$2:$E$96,"yes") -> 5 | I6: =H6/H2 -> 0.052631579
A7: 1078652 | B7: CVD | C7: =VLOOKUP(B7,Wikidata_upec_chemical_20!$C:$O,13,FALSE) -> ok | D7: =IF(VLOOKUP(B7,Wikidata_upec_chemical_20!$C:$O,3,FALSE)<>0,"yes","no") -> no | E7: =IF(VLOOKUP(B7,Wikidata_upec_chemical_20!$C:$O,4,FALSE)<>0,"yes","no") -> no
A8: 1078896 | B8: 3D numerical simulations | C8: =VLOOKUP(B8,Wikidata_upec_chemical_20!$C:$O,13,FALSE) -> ok | D8: =IF(VLOOKUP(B8,Wikidata_upec_chemical_20!$C:$O,3,FALSE)<>0,"yes","no") -> no | E8: =IF(VLOOKUP(B8,Wikidata_upec_chemical_20!$C:$O,4,FALSE)<>0,"yes","no") -> no
A9: 1083001 | B9: Design of experiments | C9: =VLOOKUP(B9,Wikidata_upec_chemical_20!$C:$O,13,FALSE) -> Ok | D9: =IF(VLOOKUP(B9,Wikidata_upec_chemical_20!$C:$O,3,FALSE)<>0,"yes","no") -> yes | E9: =IF(VLOOKUP(B9,Wikidata_upec_chemical_20!$C:$O,4,FALSE)<>0,"yes","no") -> no
A10: 1083004 | B10: Corrosion | C10: =VLOOKUP(B10,Wikidata_upec_chemical_20!$C:$O,13,FALSE) -> Wrong | D10: =IF(VLOOKUP(B10,Wikidata_upec_chemical_20!$C:$O,3,FALSE)<>0,"yes","no") -> yes | E10: =IF(VLOOKUP(B10,Wikidata_upec_chemical_20!$C:$O,4,FALSE)<>0,"yes","no") -> no
A11: 1083007 | B11: Ni-MH batteries | C11: =VLOOKUP(B11,Wikidata_upec_chemical_20!$C:$O,13,FALSE) -> ok | D11: =IF(VLOOKUP(B11,Wikidata_upec_chemical_20!$C:$O,3,FALSE)<>0,"yes","no") -> no | E11: =IF(VLOOKUP(B11,Wikidata_upec_chemical_20!$C:$O,4,FALSE)<>0,"yes","no") -> no
A12: 1083014 | B12: Raman micro spectroscopy | C12: =VLOOKUP(B12,Wikidata_upec_chemical_20!$C:$O,13,FALSE) -> ok | D12: =IF(VLOOKUP(B12,Wikidata_upec_chemical_20!$C:$O,3,FALSE)<>0,"yes","no") -> no | E12: =IF(VLOOKUP(B12,Wikidata_upec_chemical_20!$C:$O,4,FALSE)<>0,"yes","no") -> no
A13: 1083157 | B13: TEM | C13: =VLOOKUP(B13,Wikidata_upec_chemical_20!$C:$O,13,FALSE) -> Ok | D13: =IF(VLOOKUP(B13,Wikidata_upec_chemical_20!$C:$O,3,FALSE)<>0,"yes","no") -> yes | E13: =IF(VLOOKUP(B13,Wikidata_upec_chemical_20!$C:$O,4,FALSE)<>0,"yes","no") -> yes
A14: 1083160 | B14: Combination of techniques | C14: =VLOOKUP(B14,Wikidata_upec_chemical_20!$C:$O,13,FALSE) -> ok | D14: =IF(VLOOKUP(B14,Wikidata_upec_chemical_20!$C:$O,3,FALSE)<>0,"yes","no") -> no | E14: =IF(VLOOKUP(B14,Wikidata_upec_chemical_20!$C:$O,4,FALSE)<>0,"yes","no") -> no
A15: 1084520 | B15: 20902069 | C15: =VLOOKUP(B15,Wikidata_upec_chemical_20!$C:$O,13,FALSE) -> ok | D15: =IF(VLOOKUP(B15,Wikidata_upec_chemical_20!$C:$O,3,FALSE)<>0,"yes","no") -> no | E15: =IF(VLOOKUP(B15,Wikidata_upec_chemical_20!$C:$O,4,FALSE)<>0,"yes","no") -> no
A16: 1084657 | B16: Nsfc | C16: =VLOOKUP(B16,Wikidata_upec_chemical_20!$C:$O,13,FALSE) -> ok | D16: =IF(VLOOKUP(B16,Wikidata_upec_chemical_20!$C:$O,3,FALSE)<>0,"yes","no") -> no | E16: =IF(VLOOKUP(B16,Wikidata_upec_chemical_20!$C:$O,4,FALSE)<>0,"yes","no") -> no
A17: 1084678 | B17: National natural science foundation of china | C17: =VLOOKUP(B17,Wikidata_upec_chemical_20!$C:$O,13,FALSE) -> ok | D17: =IF(VLOOKUP(B17,Wikidata_upec_chemical_20!$C:$O,3,FALSE)<>0,"yes","no") -> yes | E17: =IF(VLOOKUP(B17,Wikidata_upec_chemical_20!$C:$O,4,FALSE)<>0,"yes","no") -> no
A18: 1086746 | B18: 21074094 | C18: =VLOOKUP(B18,Wikidata_upec_chemical_20!$C:$O,13,FALSE) -> ok | D18: =IF(VLOOKUP(B18,Wikidata_upec_chemical_20!$C:$O,3,FALSE)<>0,"yes","no") -> no | E18: =IF(VLOOKUP(B18,Wikidata_upec_chemical_20!$C:$O,4,FALSE)<>0,"yes","no") -> no
A19: 1086752 | B19: 51173134 | C19: =VLOOKUP(B19,Wikidata_upec_chemical_20!$C:$O,13,FALSE) -> ok | D19: =IF(VLOOKUP(B19,Wikidata_upec_chemical_20!$C:$O,3,FALSE)<>0,"yes","no") -> no | E19: =IF(VLOOKUP(B19,Wikidata_upec_chemical_20!$C:$O,4,FALSE)<>0,"yes","no") -> no
A20: 1087358 | B20: Potential curves | C20: =VLOOKUP(B20,Wikidata_upec_chemical_20!$C:$O,13,FALSE) -> ok | D20: =IF(VLOOKUP(B20,Wikidata_upec_chemical_20!$C:$O,3,FALSE)<>0,"yes","no") -> no | E20: =IF(VLOOKUP(B20,Wikidata_upec_chemical_20!$C:$O,4,FALSE)<>0,"yes","no") -> no
A21: 1088019 | B21: Long range interactions | C21: =VLOOKUP(B21,Wikidata_upec_chemical_20!$C:$O,13,FALSE) -> ok | D21: =IF(VLOOKUP(B21,Wikidata_upec_chemical_20!$C:$O,3,FALSE)<>0,"yes","no") -> no | E21: =IF(VLOOKUP(B21,Wikidata_upec_chemical_20!$C:$O,4,FALSE)<>0,"yes","no") -> no
A22: 0 | B22: Ab-initio calculations | C22: =VLOOKUP(B22,Wikidata_upec_chemical_20!$C:$O,13,FALSE) -> ok | D22: =IF(VLOOKUP(B22,Wikidata_upec_chemical_20!$C:$O,3,FALSE)<>0,"yes","no") -> no | E22: =IF(VLOOKUP(B22,Wikidata_upec_chemical_20!$C:$O,4,FALSE)<>0,"yes","no") -> no
B23: Hydrogen halides | C23: =VLOOKUP(B23,Wikidata_upec_chemical_20!$C:$O,13,FALSE) -> ok | D23: =IF(VLOOKUP(B23,Wikidata_upec_chemical_20!$C:$O,3,FALSE)<>0,"yes","no") -> yes | E23: =IF(VLOOKUP(B23,Wikidata_upec_chemical_20!$C:$O,4,FALSE)<>0,"yes","no") -> no
B24: 5210 PLANETARY SCIENCES ASTROBIOLOGY Planetary atmospheres | C24: =VLOOKUP(B24,Wikidata_upec_chemical_20!$C:$O,13,FALSE) -> ok | D24: =IF(VLOOKUP(B24,Wikidata_upec_chemical_20!$C:$O,3,FALSE)<>0,"yes","no") -> no | E24: =IF(VLOOKUP(B24,Wikidata_upec_chemical_20!$C:$O,4,FALSE)<>0,"yes","no") -> no
B25: Clouds | C25: =VLOOKUP(B25,Wikidata_upec_chemical_20!$C:$O,13,FALSE) -> Wrong | D25: =IF(VLOOKUP(B25,Wikidata_upec_chemical_20!$C:$O,3,FALSE)<>0,"yes","no") -> yes | E25: =IF(VLOOKUP(B25,Wikidata_upec_chemical_20!$C:$O,4,FALSE)<>0,"yes","no") -> no
B26: And hazes | C26: =VLOOKUP(B26,Wikidata_upec_chemical_20!$C:$O,13,FALSE) -> ok | D26: =IF(VLOOKUP(B26,Wikidata_upec_chemical_20!$C:$O,3,FALSE)<>0,"yes","no") -> no | E26: =IF(VLOOKUP(B26,Wikidata_upec_chemical_20!$C:$O,4,FALSE)<>0,"yes","no") -> no
B27: 5405 PLANETARY SCIENCES SOLID SURFACE PLANETS Atmospheres | C27: =VLOOKUP(B27,Wikidata_upec_chemical_20!$C:$O,13,FALSE) -> ok | D27: =IF(VLOOKUP(B27,Wikidata_upec_chemical_20!$C:$O,3,FALSE)<>0,"yes","no") -> no | E27: =IF(VLOOKUP(B27,Wikidata_upec_chemical_20!$C:$O,4,FALSE)<>0,"yes","no") -> no
B28: 0305 ATMOSPHERIC COMPOSITION AND STRUCTURE Aerosols and particles | C28: =VLOOKUP(B28,Wikidata_upec_chemical_20!$C:$O,13,FALSE) -> ok | D28: =IF(VLOOKUP(B28,Wikidata_upec_chemical_20!$C:$O,3,FALSE)<>0,"yes","no") -> no | E28: =IF(VLOOKUP(B28,Wikidata_upec_chemical_20!$C:$O,4,FALSE)<>0,"yes","no") -> no
B29: Parallel Charging | C29: =VLOOKUP(B29,Wikidata_upec_chemical_20!$C:$O,13,FALSE) -> ok | D29: =IF(VLOOKUP(B29,Wikidata_upec_chemical_20!$C:$O,3,FALSE)<>0,"yes","no") -> no | E29: =IF(VLOOKUP(B29,Wikidata_upec_chemical_20!$C:$O,4,FALSE)<>0,"yes","no") -> no
B30: Parallel Tempering | C30: =VLOOKUP(B30,Wikidata_upec_chemical_20!$C:$O,13,FALSE) -> ok | D30: =IF(VLOOKUP(B30,Wikidata_upec_chemical_20!$C:$O,3,FALSE)<>0,"yes","no") -> yes | E30: =IF(VLOOKUP(B30,Wikidata_upec_chemical_20!$C:$O,4,FALSE)<>0,"yes","no") -> no
B31: Electrospray ionisation | C31: =VLOOKUP(B31,Wikidata_upec_chemical_20!$C:$O,13,FALSE) -> ok | D31: =IF(VLOOKUP(B31,Wikidata_upec_chemical_20!$C:$O,3,FALSE)<>0,"yes","no") -> no | E31: =IF(VLOOKUP(B31,Wikidata_upec_chemical_20!$C:$O,4,FALSE)<>0,"yes","no") -> no
B32: Charged droplets | C32: =VLOOKUP(B32,Wikidata_upec_chemical_20!$C:$O,13,FALSE) -> ok | D32: =IF(VLOOKUP(B32,Wikidata_upec_chemical_20!$C:$O,3,FALSE)<>0,"yes","no") -> no | E32: =IF(VLOOKUP(B32,Wikidata_upec_chemical_20!$C:$O,4,FALSE)<>0,"yes","no") -> no
B33: Charged clusters | C33: =VLOOKUP(B33,Wikidata_upec_chemical_20!$C:$O,13,FALSE) -> ok | D33: =IF(VLOOKUP(B33,Wikidata_upec_chemical_20!$C:$O,3,FALSE)<>0,"yes","no") -> no | E33: =IF(VLOOKUP(B33,Wikidata_upec_chemical_20!$C:$O,4,FALSE)<>0,"yes","no") -> no
B34: Coarse-grained models | C34: =VLOOKUP(B34,Wikidata_upec_chemical_20!$C:$O,13,FALSE) -> ok | D34: =IF(VLOOKUP(B34,Wikidata_upec_chemical_20!$C:$O,3,FALSE)<>0,"yes","no") -> yes | E34: =IF(VLOOKUP(B34,Wikidata_upec_chemical_20!$C:$O,4,FALSE)<>0,"yes","no") -> no
... B96: CRYSTALLIZATION | C96: =VLOOKUP(B96,Wikidata_upec_chemical_20!$C:$O,13,FALSE) -> ok | D96: =IF(VLOOKUP(B96,Wikidata_upec_chemical_20!$C:$O,3,FALSE)<>0,"yes","no") -> yes | E96: =IF(VLOOKUP(B96,Wikidata_upec_chemical_20!$C:$O,4,FALSE)<>0,"yes","no") -> yes
B97: 0 | D97: =IF(VLOOKUP(B97,Wikidata_upec_chemical_20!$C:$O,3,FALSE)<>0,"yes","no") -> #N/A | E97: =IF(VLOOKUP(B97,Wikidata_upec_chemical_20!$C:$O,4,FALSE)<>0,"yes","no") -> #N/A

Sheet Summary
A1: 1st round | B1: Field | C1: Total articles | D1: Total keywords | E1: Correct Wikidata label | F1: Incorrect Wikidata label | G1: # QID in Wikidata | H1: # BNF_Id | I1: % Correct Wikidata label | J1: % Incorrect Wikidata label | K1: % # QID in Wikidata | L1: % # BNF_Id
A2: Carmen | B2: Chemical Engineering | C2: =Sheet1!H1 -> 20 | D2: =Sheet1!H2 -> 95 | E2: =Sheet1!$H$3 -> 73 | F2: =Sheet1!H4 -> 22 | G2: =Sheet1!H5 -> 44 | H2: =Sheet1!H6 -> 5 | I2: =E2/D2 -> 0.76842105 | J2: =F2/D2 -> 0.23157895 | K2: =G2/$D2 -> 0.46315789 | L2: =H2/$D2 -> 0.052631579
A3: Sallay | B3: Civil Engineering | C3: =Wikidata_upec_civil_20!W7 -> 20 | D3: =Wikidata_upec_civil_20!X7 -> 93 | E3: =Wikidata_upec_civil_20!Y7 -> 67 | F3: =Wikidata_upec_civil_20!Z7 -> 26 | G3: =Wikidata_upec_civil_20!AA7 -> 43 | H3: =Wikidata_upec_civil_20!AB7 -> 7 | I3: =Wikidata_upec_civil_20!AC7 -> 0.72043011 | J3: =Wikidata_upec_civil_20!AD7 -> 0.27956989 | ... L3: =Wikidata_upec_civil_20!AF7 -> 0.075268817
A4: Bernard | B4: Civil Engineering 2 part | C4: =Wikidata_upec_civil_20_part2!W12 -> 9 | D4: =Wikidata_upec_civil_20_part2!X12 -> 48 | E4: =Wikidata_upec_civil_20_part2!Y12 -> 41 | F4: =Wikidata_upec_civil_20_part2!Z12 -> 7 | G4: =Wikidata_upec_civil_20_part2!AA12 -> 17 | H4: =Wikidata_upec_civil_20_part2!AB12 -> 2 | I4: =Wikidata_upec_civil_20_part2!AC12 -> 0.85416667 | J4: =Wikidata_upec_civil_20_part2!AD12 -> 0.14583333 | ... L4: =Wikidata_upec_civil_20_part2!AF12 -> 0.041666667
A5: King | B5: Computer Science
A6: Trizzia | B6: Marketing
A7: Diego | B7: Political Science
